{
  "info": {
    "key": "b9720_0318"
  },
  "sheets": {
    "מזומנים": {
      "columns": [
        "שם המנפיק/שם נייר ערך",
        "מספר ני\"ע",
        "מספר מנפיק",
        "דירוג",
        "שם מדרג",
        "סוג מטבע",
        "שיעור ריבית",
        "תשואה לפידיון",
        "שווי שוק",
        "שעור מנכסי אפיק ההשקעה",
        "שעור מסך נכסי השקעה"
      ],
      "data": [
        [
          "עו'ש- בנק מזרחי",
          "1111111111- 20- בנק מזרחי",
          20,
          "AAA.IL",
          "S&P מעלות",
          "שקל חדש",
          0,
          0,
          3982.229,
          98.11,
          13.87
        ],
        [
          "אירו-100- בנק מזרחי",
          "100- 20- בנק מזרחי",
          20,
          "AAA.IL",
          "S&P מעלות",
          "אירו",
          0,
          0,
          1.405649664,
          0.03,
          0.0
        ],
        [
          "דולר -20001- בנק מזרחי",
          "20001- 20- בנק מזרחי",
          20,
          "AAA.IL",
          "S&P מעלות",
          "דולר אמריקאי",
          0,
          0,
          75.40152165,
          1.86,
          0.26
        ]
      ]
    },
    "אג\"ח קונצרני": {
      "columns": [
        "שם המנפיק/שם נייר ערך",
        "מספר ני\"ע",
        "זירת מסחר",
        "ספק מידע",
        "מספר מנפיק",
        "ענף מסחר",
        "דירוג",
        "שם מדרג",
        "תאריך רכישה",
        "מח\"מ",
        "סוג מטבע",
        "שיעור ריבית",
        "תשואה לפידיון",
        "ערך נקוב",
        "שער",
        "פדיון/ ריבית לקבל",
        "שווי שוק",
        "שעור מערך נקוב מונפק",
        "שעור מנכסי אפיק ההשקעה",
        "שעור מסך נכסי השקעה"
      ],
      "data": [
        [
          "חלל תקש  אגח טז- חלל",
          1139922,
          "TASE",
          "אחר",
          1132,
          "תקשורת ומדיה",
          0,
          "לא מדורג",
          "25/01/17",
          4.55,
          "שקל חדש",
          5.95,
          7.47,
          14246,
          90.69,
          0,
          12.9196974,
          0,
          100,
          0.05
        ]
      ]
    },
    "מניות": {
      "columns": [
        "שם המנפיק/שם נייר ערך",
        "מספר ני\"ע",
        "זירת מסחר",
        "ספק מידע",
        "מספר מנפיק",
        "ענף מסחר",
        "סוג מטבע",
        "ערך נקוב",
        "שער",
        "פדיון/ ריבית לקבל",
        "שווי שוק",
        "שעור מערך נקוב מונפק",
        "שעור מנכסי אפיק ההשקעה",
        "שעור מסך נכסי השקעה"
      ],
      "data": [
        [
          "פניקס    1- הפניקס אחזקות",
          767012,
          "TASE",
          "אחר",
          767,
          "ביטוח",
          "שקל חדש",
          11608.0,
          2198.0,
          0.0,
          255.14384,
          0.0,
          1.44,
          0.89
        ],
        [
          "אלביט מערכות",
          1081124,
          "TASE",
          "אחר",
          1040,
          "ביטחוניות",
          "שקל חדש",
          630.0,
          46120.0,
          0.0,
          290.556,
          0.0,
          1.64,
          1.01
        ],
        [
          "דיסקונט- דיסקונט",
          691212,
          "TASE",
          "אחר",
          691,
          "בנקים",
          "שקל חדש",
          44836.0,
          1213.0,
          0.0,
          543.86068,
          0.0,
          3.07,
          1.89
        ],
        [
          "בינלאומי 5- הבינלאומי",
          593038,
          "TASE",
          "אחר",
          593,
          "בנקים",
          "שקל חדש",
          3894.0,
          8209.0,
          0.0,
          319.65846,
          0.0,
          1.8,
          1.11
        ],
        [
          "מזרחי- מזרחי טפחות הנפק",
          695437,
          "TASE",
          "אחר",
          231,
          "בנקים",
          "שקל חדש",
          6529.0,
          6372.0,
          0.0,
          416.02788,
          0.0,
          2.35,
          1.45
        ],
        [
          "פועלים",
          662577,
          "TASE",
          "אחר",
          662,
          "בנקים",
          "שקל חדש",
          22035.0,
          2664.0,
          0.0,
          587.0124,
          0.0,
          3.31,
          2.05
        ],
        [
          "בזן- בתי זיקוק",
          2590248,
          "TASE",
          "אחר",
          259,
          "חיפושי נפט וגז",
          "שקל חדש",
          233524.0,
          181.2,
          0.0,
          423.145488,
          0.01,
          2.39,
          1.47
        ],
        [
          "דלק קד יהש- דלק קידוחים",
          475020,
          "TASE",
          "אחר",
          475,
          "חיפושי נפט וגז",
          "שקל חדש",
          16258.83,
          1079.0,
          0.0,
          175.4327757,
          0.0,
          0.99,
          0.61
        ],
        [
          "ישרמקו יהש- ישראמקו",
          232017,
          "TASE",
          "אחר",
          232,
          "חיפושי נפט וגז",
          "שקל חדש",
          392608.0,
          42.5,
          0.0,
          166.8584,
          0.0,
          0.94,
          0.58
        ],
        [
          "פז נפט- פז נפט",
          1100007,
          "TASE",
          "אחר",
          1363,
          "חיפושי נפט וגז",
          "שקל חדש",
          857.0,
          57050.0,
          0.0,
          488.9185,
          0.01,
          2.76,
          1.7
        ],
        [
          "טבע- טבע",
          629014,
          "TASE",
          "אחר",
          629,
          "כימיה, גומי ופלסטיק",
          "שקל חדש",
          2158.0,
          7973.0,
          0.0,
          172.05734,
          0.0,
          0.97,
          0.6
        ],
        [
          "טאואר- טאואר",
          1082379,
          "TASE",
          "אחר",
          2028,
          "מוליכים למחצה",
          "שקל חדש",
          3390.44,
          7920.0,
          0.0,
          268.522848,
          0.0,
          1.52,
          0.94
        ],
        [
          "פרוטרום- פרוטרום תעשיות",
          1081082,
          "TASE",
          "אחר",
          1037,
          "מזון",
          "שקל חדש",
          1542.0,
          37650.0,
          0.0,
          580.563,
          0.0,
          3.28,
          2.02
        ],
        [
          "מזור- מזור",
          1106855,
          "TASE",
          "אחר",
          4100,
          "מכשור רפואי",
          "שקל חדש",
          1176.0,
          10450.0,
          0.0,
          122.892,
          0.0,
          0.69,
          0.43
        ],
        [
          "כיל- כיל",
          281014,
          "TASE",
          "אחר",
          281,
          "מסחר",
          "שקל חדש",
          57237.0,
          2220.0,
          0.0,
          1270.6614,
          0.0,
          7.17,
          4.43
        ],
        [
          "פריגו (חדש)- פריגו חדשה",
          1130699,
          "TASE",
          "אחר",
          1612,
          "מסחר",
          "שקל חדש",
          627.0,
          26080.0,
          0.0,
          163.5216,
          0.0,
          0.92,
          0.57
        ],
        [
          "שופרסל- שופרסל",
          777037,
          "TASE",
          "אחר",
          777,
          "מסחר",
          "שקל חדש",
          15367.0,
          2330.0,
          0.0,
          358.0511,
          0.01,
          2.02,
          1.25
        ],
        [
          "אירפורט סיטי- איירפורט",
          1095835,
          "TASE",
          "אחר",
          1300,
          "נדל\"ן ובינוי",
          "שקל חדש",
          14211.89,
          4440.0,
          0.0,
          631.007916,
          0.01,
          3.56,
          2.2
        ],
        [
          "אלוני חץ- אלוני חץ",
          390013,
          "TASE",
          "אחר",
          390,
          "נדל\"ן ובינוי",
          "שקל חדש",
          1705.0,
          3824.0,
          0.0,
          65.1992,
          0.0,
          0.37,
          0.23
        ],
        [
          "אמות- אמות",
          1097278,
          "TASE",
          "אחר",
          1328,
          "נדל\"ן ובינוי",
          "שקל חדש",
          3288.0,
          1920.0,
          0.0,
          63.1296,
          0.0,
          0.36,
          0.22
        ],
        [
          "גזית גלוב- גזית גלוב",
          126011,
          "TASE",
          "אחר",
          126,
          "נדל\"ן ובינוי",
          "שקל חדש",
          1584.0,
          3315.0,
          0.60192,
          53.11152,
          0.0,
          0.3,
          0.19
        ],
        [
          "עזריאלי קבוצה",
          1119478,
          "TASE",
          "אחר",
          1420,
          "נדל\"ן ובינוי",
          "שקל חדש",
          3314.0,
          18680.0,
          0.0,
          619.0552,
          0.0,
          3.5,
          2.16
        ],
        [
          "אורמת טכנו- אורמת טכנו",
          1134402,
          "TASE",
          "אחר",
          2250,
          "קלינטק",
          "שקל חדש",
          1743.0,
          19130.0,
          0.0,
          333.4359,
          0.0,
          1.88,
          1.16
        ],
        [
          "נייס",
          273011,
          "TASE",
          "אחר",
          273,
          "תוכנה ואינטרנט",
          "שקל חדש",
          792.0,
          41150.0,
          0.0,
          325.908,
          0.0,
          1.84,
          1.14
        ],
        [
          "בזק- בזק",
          230011,
          "TASE",
          "אחר",
          230,
          "תקשורת ומדיה",
          "שקל חדש",
          96090.0,
          418.3,
          11.04927,
          412.99374,
          0.0,
          2.33,
          1.44
        ],
        [
          "פוקס- פוקס",
          1087022,
          "TASE",
          "אחר",
          1140,
          "אופנה והלבשה",
          "שקל חדש",
          592.0,
          7451.0,
          0.0,
          44.10992,
          0.0,
          0.25,
          0.15
        ],
        [
          "מיטרוניקס",
          1091065,
          "TASE",
          "אחר",
          1212,
          "אלקטרוניקה ואופטיקה",
          "שקל חדש",
          8248.81,
          2362.0,
          0.0,
          194.8368922,
          0.01,
          1.1,
          0.68
        ],
        [
          "קמהדע- קמהדע",
          1094119,
          "TASE",
          "אחר",
          1267,
          "ביוטכנולוגיה",
          "שקל חדש",
          1673.0,
          2245.0,
          0.0,
          37.55885,
          0.0,
          0.21,
          0.13
        ],
        [
          "איידיאיי ביטוח",
          1129501,
          "TASE",
          "אחר",
          1608,
          "ביטוח",
          "שקל חדש",
          256.0,
          22400.0,
          0.0,
          57.344,
          0.0,
          0.32,
          0.2
        ],
        [
          "כלל ביטוח- כלל ביטוח",
          224014,
          "TASE",
          "אחר",
          224,
          "ביטוח",
          "שקל חדש",
          148.0,
          6850.0,
          0.0,
          10.138,
          0.0,
          0.06,
          0.04
        ],
        [
          "מגדל ביטוח- מגדל ביטוח הון",
          1081165,
          "TASE",
          "אחר",
          1597,
          "ביטוח",
          "שקל חדש",
          24809.0,
          403.6,
          0.0,
          100.129124,
          0.0,
          0.57,
          0.35
        ],
        [
          "מנורה    1- מנורה מבטחים הח",
          566018,
          "TASE",
          "אחר",
          566,
          "ביטוח",
          "שקל חדש",
          1908.0,
          4128.0,
          0.0,
          78.76224,
          0.0,
          0.44,
          0.27
        ],
        [
          "אגוד- בנק אגוד",
          722314,
          "TASE",
          "אחר",
          722,
          "בנקים",
          "שקל חדש",
          4695.0,
          1673.0,
          0.0,
          78.54735,
          0.01,
          0.44,
          0.27
        ],
        [
          "חברה לישראל- החברה לישראל",
          576017,
          "TASE",
          "אחר",
          576,
          "השקעה ואחזקות",
          "שקל חדש",
          28.0,
          116900.0,
          0.0,
          32.732,
          0.0,
          0.18,
          0.11
        ],
        [
          "קנון- קנון החזקות",
          1134139,
          "TASE",
          "אחר",
          1635,
          "השקעה ואחזקות",
          "שקל חדש",
          2326.0,
          6178.0,
          0.0,
          143.70028,
          0.0,
          0.81,
          0.5
        ],
        [
          "נובה- נובה",
          1084557,
          "TASE",
          "אחר",
          2177,
          "מוליכים למחצה",
          "שקל חדש",
          2248.0,
          9411.0,
          0.0,
          211.55928,
          0.01,
          1.19,
          0.74
        ],
        [
          "קרור     1- קרור",
          621011,
          "TASE",
          "אחר",
          621,
          "מזון",
          "שקל חדש",
          734.0,
          9761.0,
          0.0,
          71.64574,
          0.01,
          0.4,
          0.25
        ],
        [
          "שפיר הנדסה ותעשיה בע\"מ- שפיר הנדסה",
          1133875,
          "TASE",
          "אחר",
          1633,
          "מתכת ומוצרי בניה",
          "שקל חדש",
          4116.0,
          1281.0,
          0.0,
          52.72596,
          0.0,
          0.3,
          0.18
        ],
        [
          "אדגר- אדגר השקעות",
          1820083,
          "TASE",
          "אחר",
          182,
          "נדל\"ן ובינוי",
          "שקל חדש",
          30000.0,
          619.6,
          0.0,
          185.88,
          0.03,
          1.05,
          0.65
        ],
        [
          "אשטרום נכס- אשטרום נכסים",
          251017,
          "TASE",
          "אחר",
          251,
          "נדל\"ן ובינוי",
          "שקל חדש",
          4133.0,
          1651.0,
          0.0,
          68.23583,
          0.01,
          0.39,
          0.24
        ],
        [
          "ביג",
          1097260,
          "TASE",
          "אחר",
          1327,
          "נדל\"ן ובינוי",
          "שקל חדש",
          154.0,
          25460.0,
          0.0,
          39.2084,
          0.0,
          0.22,
          0.14
        ],
        [
          "בראק אן וי- בראק אן וי",
          1121607,
          "TASE",
          "אחר",
          1560,
          "נדל\"ן ובינוי",
          "שקל חדש",
          603.0,
          41320.0,
          0.0,
          249.1596,
          0.01,
          1.41,
          0.87
        ],
        [
          "כלכלית  ים- כלכלית",
          198010,
          "TASE",
          "אחר",
          198,
          "נדל\"ן ובינוי",
          "שקל חדש",
          28808.0,
          1020.0,
          0.0,
          293.8416,
          0.01,
          1.66,
          1.02
        ],
        [
          "סאמיט",
          1081686,
          "TASE",
          "אחר",
          1060,
          "נדל\"ן ובינוי",
          "שקל חדש",
          2632.0,
          3438.0,
          0.0,
          90.48816,
          0.0,
          0.51,
          0.32
        ],
        [
          "סלע נדל\"ן- סלע נדלן",
          1109644,
          "TASE",
          "אחר",
          1514,
          "נדל\"ן ובינוי",
          "שקל חדש",
          22802.0,
          649.4,
          0.0,
          148.076188,
          0.02,
          0.84,
          0.52
        ],
        [
          "אבגול- אבגול",
          1100957,
          "TASE",
          "אחר",
          1390,
          "עץ, נייר ודפוס",
          "שקל חדש",
          7788.0,
          402.7,
          0.0,
          31.362276,
          0.0,
          0.18,
          0.11
        ],
        [
          "גילת- גילת",
          1082510,
          "TASE",
          "אחר",
          2030,
          "ציוד תקשורת",
          "שקל חדש",
          727.22,
          3175.0,
          0.0,
          23.089235,
          0.0,
          0.13,
          0.08
        ],
        [
          "אנלייט אנרגיה- אנלייט אנרגיה",
          720011,
          "TASE",
          "אחר",
          720,
          "קלינטק",
          "שקל חדש",
          41058.0,
          190.0,
          0.0,
          78.0102,
          0.01,
          0.44,
          0.27
        ],
        [
          "חילן- חילן",
          1084698,
          "TASE",
          "אחר",
          1110,
          "שירותי מידע",
          "שקל חדש",
          931.0,
          9054.0,
          0.931,
          85.22374,
          0.0,
          0.48,
          0.3
        ],
        [
          "רומטק -מטריקס- מטריקס",
          445015,
          "TASE",
          "אחר",
          445,
          "שירותי מידע",
          "שקל חדש",
          2108.0,
          4355.0,
          0.0,
          91.8034,
          0.0,
          0.52,
          0.32
        ],
        [
          "מלם תים- מלם-תים",
          156018,
          "TASE",
          "אחר",
          156,
          "שירותי מידע",
          "שקל חדש",
          32.0,
          36900.0,
          0.0,
          11.808,
          0.0,
          0.07,
          0.04
        ],
        [
          "פורמולה- פורמולה",
          256016,
          "TASE",
          "אחר",
          256,
          "שירותי מידע",
          "שקל חדש",
          615.0,
          15280.0,
          0.0,
          93.972,
          0.0,
          0.53,
          0.33
        ],
        [
          "דנאל כא- דנאל אדיר",
          314013,
          "TASE",
          "אחר",
          314,
          "שירותים",
          "שקל חדש",
          30.0,
          19400.0,
          0.0,
          5.82,
          0.0,
          0.03,
          0.02
        ],
        [
          "נאוי- נאוי",
          208017,
          "TASE",
          "אחר",
          208,
          "שירותים פיננסיים",
          "שקל חדש",
          240.0,
          2129.0,
          0.0,
          5.1096,
          0.0,
          0.03,
          0.02
        ],
        [
          "מגיק- מג'יק",
          1082312,
          "TASE",
          "אחר",
          2026,
          "תוכנה ואינטרנט",
          "שקל חדש",
          1809.0,
          3215.0,
          0.0,
          58.15935,
          0.0,
          0.33,
          0.2
        ],
        [
          "סאפינס",
          1087659,
          "TASE",
          "אחר",
          1146,
          "תוכנה ואינטרנט",
          "שקל חדש",
          985.0,
          4299.0,
          0.0,
          42.34515,
          0.0,
          0.24,
          0.15
        ],
        [
          "בי קומיוניקיישנס- בי קומיוניקיישנס",
          1107663,
          "TASE",
          "אחר",
          1422,
          "תקשורת ומדיה",
          "שקל חדש",
          130.0,
          3569.0,
          0.0,
          4.6397,
          0.0,
          0.03,
          0.02
        ],
        [
          "סלקום",
          1101534,
          "TASE",
          "אחר",
          2066,
          "תקשורת ומדיה",
          "שקל חדש",
          7636.0,
          2490.0,
          0.0,
          190.1364,
          0.01,
          1.07,
          0.66
        ],
        [
          "פרטנר- פרטנר",
          1083484,
          "TASE",
          "אחר",
          2095,
          "תקשורת ומדיה",
          "שקל חדש",
          10740.0,
          1912.0,
          0.0,
          205.3488,
          0.01,
          1.16,
          0.72
        ],
        [
          "קסטרו- קסטרו",
          280016,
          "TASE",
          "אחר",
          280,
          "אופנה והלבשה",
          "שקל חדש",
          37.0,
          10350.0,
          0.0,
          3.8295,
          0.0,
          0.02,
          0.01
        ],
        [
          "פריורטק",
          328013,
          "TASE",
          "אחר",
          328,
          "אלקטרוניקה ואופטיקה",
          "שקל חדש",
          235.0,
          3685.0,
          0.0,
          8.65975,
          0.0,
          0.05,
          0.03
        ],
        [
          "אירונאוטיקס- אירונאוטיקס",
          1141142,
          "TASE",
          "אחר",
          4850,
          "ביטחוניות",
          "שקל חדש",
          8754.0,
          843.4,
          0.0,
          73.831236,
          0.0,
          0.42,
          0.26
        ],
        [
          "פריון נטוורק- פריון נטוורק",
          1095819,
          "TASE",
          "אחר",
          2240,
          "השקעות בהיי-טק",
          "שקל חדש",
          4563.0,
          1101.0,
          0.0,
          50.23863,
          0.01,
          0.28,
          0.18
        ],
        [
          "כלל משקאות- כלל משקאות",
          1147685,
          "TASE",
          "אחר",
          4983,
          "מזון",
          "שקל חדש",
          7840.0,
          4997.0,
          0.0,
          391.7648,
          0.0,
          2.21,
          1.36
        ],
        [
          "איתמר",
          1102458,
          "TASE",
          "אחר",
          1411,
          "מכשור רפואי",
          "שקל חדש",
          125000.0,
          130.2,
          0.0,
          162.75,
          0.05,
          0.92,
          0.57
        ],
        [
          "בריינסוויי 0.01- בריינסוויי",
          1100718,
          "TASE",
          "אחר",
          1386,
          "מכשור רפואי",
          "שקל חדש",
          5100.0,
          2700.0,
          0.0,
          137.7,
          0.03,
          0.78,
          0.48
        ],
        [
          "גולף 0.01- גולף",
          1096148,
          "TASE",
          "אחר",
          1310,
          "מסחר",
          "שקל חדש",
          1379.0,
          388.3,
          0.0,
          5.354657,
          0.0,
          0.03,
          0.02
        ],
        [
          "גניגר- גניגר",
          1095892,
          "TASE",
          "אחר",
          1301,
          "מסחר",
          "שקל חדש",
          3605.0,
          2320.0,
          0.0,
          83.636,
          0.02,
          0.47,
          0.29
        ],
        [
          "יעקובי קבוצה- אחים יעקבי",
          1142421,
          "TASE",
          "אחר",
          4902,
          "נדל\"ן ובינוי",
          "שקל חדש",
          182900.0,
          112.2,
          0.0,
          205.2138,
          0.0,
          1.16,
          0.71
        ],
        [
          "איי דיי או גרופ- איי.די.או",
          505016,
          "TASE",
          "אחר",
          505,
          "נדל\"ן ובינוי",
          "שקל חדש",
          5224.0,
          7871.0,
          0.0,
          411.18104,
          0.01,
          2.32,
          1.43
        ],
        [
          "גבאי מניבים - אנגל משאבים",
          771014,
          "TASE",
          "אחר",
          771,
          "נדל\"ן ובינוי",
          "שקל חדש",
          8900.0,
          1963.0,
          0.0,
          174.707,
          0.16,
          0.99,
          0.61
        ],
        [
          "אספן גרופ- אספן גרופ",
          313015,
          "TASE",
          "אחר",
          313,
          "נדל\"ן ובינוי",
          "שקל חדש",
          1703.0,
          667.3,
          0.0,
          11.364119,
          0.0,
          0.06,
          0.04
        ],
        [
          "אפריקה מגורים",
          1097948,
          "TASE",
          "אחר",
          1338,
          "נדל\"ן ובינוי",
          "שקל חדש",
          66.0,
          6310.0,
          0.0,
          4.1646,
          0.0,
          0.02,
          0.01
        ],
        [
          "לויי בוקס נדל\"ן- וויי בוקס",
          486027,
          "TASE",
          "אחר",
          486,
          "נדל\"ן ובינוי",
          "שקל חדש",
          167026.0,
          66.8,
          0.0,
          111.573368,
          0.11,
          0.63,
          0.39
        ],
        [
          "מדיפאואר- מדיפאור",
          1139955,
          "TASE",
          "אחר",
          4903,
          "נדל\"ן ובינוי",
          "שקל חדש",
          42000.0,
          472.7,
          0.0,
          198.534,
          0.13,
          1.12,
          0.69
        ],
        [
          "רני צים- רני צים",
          1143619,
          "TASE",
          "אחר",
          4948,
          "נדל\"ן ובינוי",
          "שקל חדש",
          80000.0,
          226.5,
          0.0,
          181.2,
          0.0,
          1.02,
          0.63
        ],
        [
          "על בד- על-בד",
          625012,
          "TASE",
          "אחר",
          625,
          "עץ, נייר ודפוס",
          "שקל חדש",
          320.43,
          4216.0,
          0.0,
          13.5093288,
          0.0,
          0.08,
          0.05
        ],
        [
          "אמת- אמת",
          382010,
          "TASE",
          "אחר",
          382,
          "שירותי מידע",
          "שקל חדש",
          508.0,
          1120.0,
          0.07366,
          5.76326,
          0.0,
          0.03,
          0.02
        ],
        [
          "ORBOTECH LTD-OR",
          "IL001082338",
          "NASDAQ",
          "בלומברג",
          4674,
          "Technology Hardware & Equipment",
          "דולר אמריקאי",
          1057.0,
          5914.0,
          0.0,
          226.72732446,
          0.0,
          1.28,
          0.79
        ],
        [
          "UNIVERSAL DISPLAY-OLED",
          "US91347P1057",
          "NYSE",
          "בלומברג",
          4973,
          "Capital Goods",
          "דולר אמריקאי",
          444.0,
          12021.0,
          0.0,
          193.58474148,
          0.0,
          1.09,
          0.67
        ],
        [
          "FB - FACEBOOK",
          "US30303M1027",
          "TASE",
          "בלומברג",
          2910,
          "Media",
          "דולר אמריקאי",
          275.0,
          16244.0,
          0.0,
          162.021717,
          0.0,
          0.91,
          0.56
        ],
        [
          "CATERPILLAR",
          "US1491231015",
          "NYSE",
          "בלומברג",
          4923,
          "Other",
          "דולר אמריקאי",
          494.0,
          15228.0,
          0.0,
          272.84586264,
          0.0,
          1.54,
          0.95
        ],
        [
          "MDWD-MEDIWOUND LTD",
          "IL0011316309",
          "NYSE",
          "בלומברג",
          4717,
          "Pharmaceuticals & Biotechnology",
          "דולר אמריקאי",
          5744.0,
          639.0,
          0.0,
          133.12598832,
          0.0,
          0.75,
          0.46
        ],
        [
          "MYL-MYLAN LABORATOR- MYLAN",
          "NL0011031208",
          "NASDAQ",
          "בלומברג",
          4605,
          "Pharmaceuticals & Biotechnology",
          "דולר אמריקאי",
          4412.0,
          3648.0,
          0.0,
          583.76477952,
          0.0,
          3.3,
          2.03
        ],
        [
          "ROGEN PHARMAL - URGN",
          "IL0011407140",
          "NASDAQ",
          "בלומברג",
          4947,
          "Pharmaceuticals & Biotechnology",
          "דולר אמריקאי",
          949.0,
          4782.0,
          0.0,
          164.59753986,
          0.0,
          0.93,
          0.57
        ],
        [
          "AROUNDTOWN PROP",
          "LU1673108939",
          "FWB",
          "בלומברג",
          4845,
          "Real Estate",
          "אירו",
          9725.77,
          773.5,
          0.0,
          317.13465975282,
          0.0,
          1.79,
          1.1
        ],
        [
          "MLNX - MELLANOX",
          "IL0011017329",
          "NYSE",
          "בלומברג",
          4917,
          "Semiconductors & Semiconductor Equipment",
          "דולר אמריקאי",
          680.0,
          7345.0,
          0.0,
          181.154142,
          0.0,
          1.02,
          0.63
        ],
        [
          "MICRON TECH-INC",
          "US5951121038",
          "NYSE",
          "בלומברג",
          2360,
          "Semiconductors & Semiconductor Equipment",
          "דולר אמריקאי",
          492.0,
          4515.0,
          0.0,
          80.5694526,
          0.0,
          0.45,
          0.28
        ],
        [
          "ADOBE SYSTENS-ADBE",
          "US00724F1012",
          "NYSE",
          "בלומברג",
          4986,
          "Software & Services",
          "דולר אמריקאי",
          265.0,
          27549.0,
          0.0,
          264.78859095,
          0.0,
          1.5,
          0.92
        ],
        [
          "CHKP - CHECK POINT",
          "IL0010824113",
          "NYSE",
          "בלומברג",
          2515,
          "Software & Services",
          "דולר אמריקאי",
          460.0,
          11773.0,
          0.0,
          196.4230866,
          0.0,
          1.11,
          0.68
        ],
        [
          "MSFT -  MICROSOFT- MICROSOFT CORP",
          43893,
          "NYSE",
          "בלומברג",
          2360,
          "Software & Services",
          "דולר אמריקאי",
          647.0,
          11561.0,
          0.0,
          271.29840309,
          0.0,
          1.53,
          0.95
        ],
        [
          "SOLAREDGE",
          "US83417M1045",
          "NYSE",
          "בלומברג",
          4744,
          "Technology Hardware & Equipment",
          "דולר אמריקאי",
          1500.0,
          3790.0,
          0.0,
          206.19495,
          0.0,
          1.16,
          0.72
        ]
      ]
    },
    "תעודות סל": {
      "columns": [
        "שם המנפיק/שם נייר ערך",
        "מספר ני\"ע",
        "זירת מסחר",
        "מספר מנפיק",
        "ענף מסחר",
        "סוג מטבע",
        "ערך נקוב",
        "שער",
        "פדיון/ ריבית לקבל",
        "שווי שוק",
        "שעור מערך נקוב מונפק",
        "שעור מנכסי אפיק ההשקעה",
        "שעור מסך נכסי השקעה"
      ],
      "data": [
        [
          "קסם בנקים- קסם תעודות סל ומוצרי מדדים בע\"מ",
          1117290,
          "TASE",
          1224,
          "תעודות סל",
          "שקל חדש",
          1598,
          20310.0,
          0.0,
          324.5538,
          0.01,
          5.3,
          1.13
        ],
        [
          "הראל סל 600 שיקלי- הראל סל בע\"מ",
          1130376,
          "TASE",
          1523,
          "תעודות סל",
          "שקל חדש",
          76484,
          431.7,
          0.0,
          330.181428,
          0.03,
          5.39,
          1.15
        ],
        [
          "הראל סל S&P500- הראל סל בע\"מ",
          1116441,
          "TASE",
          1523,
          "תעודות סל",
          "דולר אמריקאי",
          36021,
          1149.0,
          0.0,
          413.88129,
          0.01,
          6.75,
          1.44
        ],
        [
          "הראל סל דקס שיקלי- הראל סל בע\"מ",
          1124189,
          "TASE",
          1523,
          "תעודות סל",
          "שקל חדש",
          3151,
          11700.0,
          0.0,
          368.667,
          0.03,
          6.02,
          1.28
        ],
        [
          "הראל סל טכנולוגיה S&P- הראל סל בע\"מ",
          1131796,
          "TASE",
          1523,
          "תעודות סל",
          "דולר אמריקאי",
          9360,
          2770.0,
          0.0,
          259.272,
          0.02,
          4.23,
          0.9
        ],
        [
          "הראל סל שקלי S&P500- הראל סל בע\"מ",
          1123249,
          "TASE",
          1523,
          "תעודות סל",
          "שקל חדש",
          4515,
          3134.0,
          0.0,
          141.5001,
          0.0,
          2.31,
          0.49
        ],
        [
          "פסגות סל נאסדק 100- פסגות תעודות סל בע\"מ",
          1118801,
          "TASE",
          1108,
          "תעודות סל",
          "דולר אמריקאי",
          1794,
          28770.0,
          0.0,
          516.1338,
          0.01,
          8.42,
          1.8
        ],
        [
          "קסם S&P500- קסם תעודות סל ומוצרי מדדים בע\"מ",
          1117324,
          "TASE",
          1224,
          "תעודות סל",
          "דולר אמריקאי",
          5676,
          10820.0,
          0.0,
          614.1432,
          0.01,
          10.02,
          2.14
        ],
        [
          "תכלית S&P 500- תכלית תעודות סל בע\"מ",
          1095710,
          "TASE",
          1223,
          "תעודות סל",
          "דולר אמריקאי",
          1999,
          11540.0,
          0.0,
          230.6846,
          0.01,
          3.76,
          0.8
        ],
        [
          "תכלית Stoxx  אירו שקלי- תכלית תעודות סל בע\"מ",
          1129873,
          "TASE",
          1223,
          "תעודות סל",
          "שקל חדש",
          8300,
          425.6,
          0.0,
          35.3248,
          0.0,
          0.58,
          0.12
        ],
        [
          "XLF - Financial Select- STATE STREET-SPDRS",
          "US81369Y6059",
          "NYSE",
          4640,
          "Banks",
          "דולר אמריקאי",
          3770,
          2769.0,
          0.0,
          378.6272451,
          0.0,
          6.18,
          1.32
        ],
        [
          "DAXEX  GY - DAX- BlackRock Fund Advisors",
          "DE0005933931",
          "FWB",
          2235,
          "Other",
          "אירו",
          410,
          10634.0,
          0.0,
          183.79763064,
          0.0,
          3.0,
          0.64
        ],
        [
          "SOXX - SEMICONDUCTOR- BlackRock Fund Advisors",
          347898,
          "NYSE",
          2235,
          "Other",
          "דולר אמריקאי",
          337,
          18569.0,
          0.99804159,
          227.9667429,
          0.0,
          3.72,
          0.79
        ],
        [
          "QQQQ - Nasdaq 100- INVESCO-POWERSHARES",
          "US73935A1043",
          "NASDAQ",
          4643,
          "Other",
          "דולר אמריקאי",
          340,
          18617.0,
          0.304,
          229.8851206,
          0.0,
          3.75,
          0.8
        ],
        [
          "ISHARES MSCI EU- ISHARES",
          408906,
          "LSE",
          4601,
          "Other",
          "דולר אמריקאי",
          930,
          2014.0,
          0.0,
          67.9344354,
          0.0,
          1.11,
          0.24
        ],
        [
          "MTUM - ISHARES MSCI US",
          "US46432F3964",
          "NYSE",
          4601,
          "Other",
          "דולר אמריקאי",
          1330,
          11962.0,
          1.27797345,
          578.31408765,
          0.0,
          9.44,
          2.01
        ],
        [
          "CSI-KWEB CHINA",
          "US5007673065",
          "NYSE",
          4868,
          "Other",
          "דולר אמריקאי",
          1340,
          4869.0,
          0.0,
          236.6421642,
          0.0,
          3.86,
          0.82
        ],
        [
          "SPY - S&P 500",
          "US78462F1030",
          "NYSE",
          4640,
          "Other",
          "דולר אמריקאי",
          560,
          29173.0,
          2.0105,
          594.5491376,
          0.0,
          9.7,
          2.07
        ],
        [
          "XLK - Technology- STATE STREET-SPDRS",
          "US81369Y8030",
          "NYSE",
          4640,
          "Other",
          "דולר אמריקאי",
          645,
          7569.0,
          0.0,
          177.07032135,
          0.0,
          2.89,
          0.62
        ],
        [
          "VANGAURD VALUE ETF -VTV- VANGUARD",
          "US9229087443",
          "NYSE",
          2990,
          "Other",
          "דולר אמריקאי",
          540,
          11115.0,
          1.43212095,
          219.12828795,
          0.0,
          3.58,
          0.76
        ]
      ]
    },
    "קרנות נאמנות": {
      "columns": [
        "שם המנפיק/שם נייר ערך",
        "מספר ני\"ע",
        "זירת מסחר",
        "מספר מנפיק",
        "ענף מסחר",
        "דירוג",
        "שם מדרג",
        "סוג מטבע",
        "ערך נקוב",
        "שער",
        "שווי שוק",
        "שעור מערך נקוב מונפק",
        "שעור מנכסי אפיק ההשקעה",
        "שעור מסך נכסי השקעה"
      ],
      "data": [
        [
          "MTF-DAX- מגודרת מט\"ח",
          5121546,
          "TASE",
          1597,
          "אחר",
          0,
          "לא מדורג",
          "שקל חדש",
          280432,
          105.11,
          294.7620752,
          0,
          100,
          1.03
        ]
      ]
    },
    "כתבי אופציה": {
      "columns": [
        "שם המנפיק/שם נייר ערך",
        "מספר ני\"ע",
        "זירת מסחר",
        "ענף מסחר",
        "סוג מטבע",
        "ערך נקוב",
        "שער",
        "שווי שוק",
        "שעור מערך נקוב מונפק",
        "שעור מנכסי אפיק ההשקעה",
        "שעור מסך נכסי השקעה"
      ],
      "data": [
        [
          "רני צים    אפ 4 01/04/2021- רני צים",
          1143627,
          "TASE",
          "נדל\"ן ובינוי",
          "שקל חדש",
          20000,
          44,
          8.8,
          0,
          100,
          0.03
        ]
      ]
    },
    "לא סחיר - אג\"ח קונצרני": {
      "columns": [
        "שם המנפיק/שם נייר ערך",
        "מספר ני\"ע",
        "ספק המידע",
        "מספר מנפיק",
        "ענף מסחר",
        "דירוג",
        "שם מדרג",
        "תאריך רכישה",
        "מח\"מ",
        "סוג מטבע",
        "שיעור ריבית",
        "תשואה לפידיון",
        "ערך נקוב",
        "שער",
        "שווי הוגן",
        "שעור מערך נקוב מונפק",
        "שעור מנכסי אפיק ההשקעה",
        "שעור מסך נכסי השקעה"
      ],
      "data": [
        [
          "אליהו הנפקות- אליהו הנפקות",
          1142009,
          "אחר",
          515703528,
          "השקעה ואחזקות",
          "A1.IL",
          "מידרוג",
          "24/09/17",
          4.68,
          "שקל חדש",
          3.85,
          4.06,
          130000,
          99.33,
          129.129,
          0,
          27.11,
          0.45
        ],
        [
          "י.ח.ק אגח א -רמ- י.ח.ק",
          1143007,
          "אחר",
          550016091,
          "השקעה ואחזקות",
          "A-.IL",
          "S&P מעלות",
          "15/01/18",
          1.98,
          "שקל חדש",
          2.57,
          3.33,
          350000,
          99.19,
          347.165,
          0,
          72.89,
          1.21
        ]
      ]
    },
    "לא סחיר - כתבי אופציה": {
      "columns": [
        "שם המנפיק/שם נייר ערך",
        "מספר ני\"ע",
        "ענף מסחר",
        "סוג מטבע",
        "תאריך רכישה",
        "ערך נקוב",
        "שער",
        "שווי הוגן",
        "שעור מערך נקוב מונפק",
        "שעור מנכסי אפיק ההשקעה",
        "שעור מסך נכסי השקעה"
      ],
      "data": [
        [
          "מגדל בטוח אפ 1- מגדל בטוח",
          110496,
          "ביטוח",
          "שקל חדש",
          "24/09/17",
          10660,
          21.19,
          2.258854,
          0,
          20.04,
          0.01
        ],
        [
          "מגדל בטוח אפ 3- מגדל בטוח",
          110498,
          "ביטוח",
          "שקל חדש",
          "24/09/17",
          10660,
          48.59,
          5.179694,
          0,
          45.96,
          0.02
        ],
        [
          "מגדל ביטוח אפ 2- מגדל בטוח",
          110497,
          "ביטוח",
          "שקל חדש",
          "24/09/17",
          10660,
          35.94,
          3.831204,
          0,
          34.0,
          0.01
        ]
      ]
    }
  }
}