{
  "info": {
    "key": "g813_0318"
  },
  "sheets": {
    "מזומנים": {
      "columns": [
        "שם המנפיק/שם נייר ערך",
        "מספר ני\"ע",
        "מספר מנפיק",
        "דירוג",
        "שם מדרג",
        "סוג מטבע",
        "שיעור ריבית",
        "תשואה לפידיון",
        "שווי שוק",
        "שעור מנכסי אפיק ההשקעה",
        "שעור מסך נכסי השקעה"
      ],
      "data": [
        [
          "עו'ש- הבנק הבינלאומי",
          "1111111111- 31- הבנק הבינלאומי",
          593,
          "AA+.il",
          "מעלות",
          "שקל חדש",
          0.0,
          0,
          2609.87224,
          64.53,
          2.52
        ],
        [
          "עו\"ש בנק מזרחי- הבנק הבינלאומי",
          "111111118- 20  הבנק מזרחי",
          695,
          "AAA.il",
          "מעלות",
          "שקל חדש",
          0.0,
          0,
          -0.16296,
          0.0,
          0.0
        ],
        [
          "דולר- הבנק הבינלאומי",
          "20001- 31- הבנק הבינלאומי",
          593,
          "AA+.il",
          "מעלות",
          "דולר אמריקאי",
          0.0,
          0,
          385.84850208,
          9.54,
          0.37
        ],
        [
          "יורו- הבנק הבינלאומי",
          "50001- 31- הבנק הבינלאומי",
          593,
          "AA+.il",
          "מעלות",
          "אירו",
          0.0,
          0,
          48.90686003,
          1.21,
          0.05
        ],
        [
          "(19) פז\"ק שבוע-3 ח'           - הבנק הבינלאומי",
          "500055341- 31- הבנק הבינלאומי",
          31,
          "AA+.IL",
          "S&P מעלות",
          "שקל חדש",
          0.05,
          0,
          1000.0651098,
          24.73,
          0.97
        ]
      ]
    },
    "תעודות התחייבות ממשלתיות": {
      "columns": [
        "שם המנפיק/שם נייר ערך",
        "מספר ני\"ע",
        "זירת מסחר",
        "דירוג",
        "שם מדרג",
        "תאריך רכישה",
        "מח\"מ",
        "סוג מטבע",
        "שיעור ריבית",
        "תשואה לפידיון",
        "ערך נקוב",
        "שער",
        "פדיון/ריבית/דיבידנד לקבל",
        "שווי שוק",
        "שעור מערך נקוב**** מונפק",
        "שעור מנכסי אפיק ההשקעה",
        "שעור מסך נכסי השקעה"
      ],
      "data": [
        [
          "גליל 5903- מדינת ישראל",
          9590332,
          "TASE",
          "RF",
          "פנימי",
          "11/02/18",
          2.73,
          "שקל חדש",
          4.0,
          -0.01,
          2737350,
          148.85,
          0.0,
          4074.545475,
          0.02,
          10.2,
          3.94
        ],
        [
          "גליל 5904- מדינת ישראל",
          9590431,
          "TASE",
          "RF",
          "פנימי",
          "12/02/18",
          5.36,
          "שקל חדש",
          4.0,
          0.0,
          4650563,
          153.77,
          0.0,
          7151.1707251,
          0.04,
          17.9,
          6.91
        ],
        [
          "ממשל צמודה 0922- מדינת ישראל",
          1124056,
          "TASE",
          "RF",
          "פנימי",
          "12/02/18",
          3.86,
          "שקל חדש",
          2.75,
          0.0,
          1313836,
          116.98,
          37.73442,
          1574.6597728,
          0.01,
          3.94,
          1.52
        ],
        [
          "ממשל צמודה 0923- מדינת ישראל",
          1128081,
          "TASE",
          "RF",
          "פנימי",
          "12/02/18",
          4.85,
          "שקל חדש",
          1.75,
          0.0,
          2315272,
          111.8,
          41.5477,
          2630.021796,
          0.02,
          6.58,
          2.54
        ],
        [
          "ממשל צמודה 1019- מדינת ישראל",
          1114750,
          "TASE",
          "RF",
          "פנימי",
          "28/02/18",
          1.06,
          "שקל חדש",
          3.0,
          -0.01,
          2231436,
          118.16,
          0.0,
          2636.6647776,
          0.01,
          6.6,
          2.55
        ],
        [
          "ממשל צמודה 1020- מדינת ישראל",
          1137181,
          "TASE",
          "RF",
          "פנימי",
          "12/02/18",
          2.09,
          "שקל חדש",
          0.1,
          -0.01,
          2546955,
          102.87,
          0.0,
          2620.0526085,
          0.02,
          6.56,
          2.53
        ],
        [
          "מ.ק.מ. 419- מדינת ישראל",
          8190415,
          "TASE",
          "RF",
          "פנימי",
          "10/04/18",
          0.51,
          "שקל חדש",
          0.0,
          0.0,
          850000,
          99.91,
          0.0,
          849.235,
          0.01,
          2.13,
          0.82
        ],
        [
          "ממשל שקלית 0120- מדינת ישראל",
          1115773,
          "TASE",
          "RF",
          "פנימי",
          "28/02/18",
          1.3,
          "שקל חדש",
          5.0,
          0.0,
          2862258,
          109.6,
          0.0,
          3137.034768,
          0.02,
          7.85,
          3.03
        ],
        [
          "ממשל שקלית 0122- מדינת ישראל",
          1123272,
          "TASE",
          "RF",
          "פנימי",
          "12/02/18",
          3.07,
          "שקל חדש",
          5.5,
          0.01,
          1733181,
          118.75,
          0.0,
          2058.1524375,
          0.01,
          5.15,
          1.99
        ],
        [
          "ממשל שקלית 0323- מדינת ישראל",
          1126747,
          "TASE",
          "RF",
          "פנימי",
          "08/04/18",
          4.14,
          "שקל חדש",
          4.24,
          0.01,
          2739478,
          115.5,
          0.0,
          3164.09709,
          0.01,
          7.92,
          3.06
        ],
        [
          "ממשל שקלית 0324- מדינת ישראל",
          1130848,
          "TASE",
          "RF",
          "פנימי",
          "25/03/18",
          5.03,
          "שקל חדש",
          3.74,
          0.01,
          1821005,
          114.03,
          0.0,
          2076.4920015,
          0.01,
          5.2,
          2.01
        ],
        [
          "ממשל שקלית 1026- מדינת ישראל",
          1099456,
          "TASE",
          "RF",
          "פנימי",
          "15/08/18",
          6.53,
          "שקל חדש",
          6.25,
          0.02,
          1743475,
          138.05,
          0.0,
          2406.8672375,
          0.01,
          6.02,
          2.33
        ],
        [
          "ממשל שקלית0327- מדינת ישראל",
          1139344,
          "TASE",
          "RF",
          "פנימי",
          "15/08/18",
          7.83,
          "שקל חדש",
          2.0,
          0.02,
          132337,
          101.03,
          0.0,
          133.7000711,
          0.0,
          0.33,
          0.13
        ],
        [
          "ISRAEL 3 1/4 01/17/28- מדינת ישראל",
          "US46513YJH27",
          "NYSE",
          "A1",
          "Moodys",
          "27/02/18",
          3.74,
          "דולר אמריקאי",
          3.25,
          7.87,
          632000,
          96.809,
          0.0,
          2201.98653512,
          0.06,
          5.51,
          2.13
        ],
        [
          "ISRAEL 3.15  06/30/23- STATE OF ISRAEL",
          "US4651387M19",
          "NYSE",
          "A1",
          "Moodys",
          "12/02/18",
          3.41,
          "דולר אמריקאי",
          3.15,
          4.34,
          600000,
          99.625,
          0.0,
          2151.30225,
          0.06,
          5.38,
          2.08
        ],
        [
          "T 2 3/4 04/30/23- US TREASURY N/B",
          "US9128284L18",
          "NYSE",
          "Aaa",
          "Moodys",
          "03/05/18",
          2.95,
          "דולר אמריקאי",
          2.75,
          4.23,
          302000,
          100.27135465562914,
          0.0,
          1089.84734832494,
          0.0,
          2.73,
          1.05
        ]
      ]
    },
    "אג\"ח קונצרני": {
      "columns": [
        "שם המנפיק/שם נייר ערך",
        "מספר ני\"ע",
        "זירת מסחר",
        "ספק מידע",
        "מספר מנפיק",
        "ענף מסחר",
        "דירוג",
        "שם מדרג",
        "תאריך רכישה",
        "מח\"מ",
        "סוג מטבע",
        "שיעור ריבית",
        "תשואה לפידיון",
        "ערך נקוב",
        "שער",
        "פדיון/ריבית/דיבידנד לקבל",
        "שווי שוק",
        "שעור מערך נקוב מונפק",
        "שעור מנכסי אפיק ההשקעה",
        "שעור מסך נכסי השקעה"
      ],
      "data": [
        [
          "לאומי אגח 179- בנק לאומי לישראל בע\"מ",
          6040372,
          "TASE",
          "אחר",
          520018078,
          "בנקים",
          "AAA.IL",
          "S&P מעלות",
          "21/06/18",
          6.58,
          "שקל חדש",
          0.83,
          0.01,
          108000.0,
          100.83,
          0.0,
          108.8964,
          0.01,
          0.2,
          0.11
        ],
        [
          "מז טפ הנפק 42- מזרחי טפחות חברה להנפקות בע\"מ",
          2310183,
          "TASE",
          "אחר",
          520032046,
          "בנקים",
          "AAA.IL",
          "S&P מעלות",
          "03/10/17",
          11.2,
          "שקל חדש",
          0.47,
          0.01,
          84981.0,
          102.15,
          0.0,
          86.8080915,
          0.01,
          0.16,
          0.08
        ],
        [
          "פועלים הנפ הת י- הפועלים הנפקות בע\"מ",
          1940402,
          "TASE",
          "אחר",
          520032640,
          "בנקים",
          "AA+.IL",
          "S&P מעלות",
          "05/03/18",
          1.47,
          "שקל חדש",
          4.1,
          0.0,
          313222.5,
          131.94,
          0.0,
          413.2657665,
          0.01,
          0.76,
          0.4
        ],
        [
          "איירפורט אגח 5- איירפורט סיטי בע\"מ",
          1133487,
          "TASE",
          "אחר",
          511659401,
          "נדל\"ן ובינוי",
          "AA.IL",
          "S&P מעלות",
          "09/08/17",
          5.44,
          "שקל חדש",
          2.34,
          0.01,
          0.16,
          107.17,
          0.0,
          0.000171472,
          0.0,
          0.0,
          0.0
        ],
        [
          "אמות אגח ג- אמות השקעות בע\"מ",
          1117357,
          "TASE",
          "אחר",
          520026683,
          "נדל\"ן ובינוי",
          "AA.IL",
          "S&P מעלות",
          "20/04/16",
          1.23,
          "שקל חדש",
          4.9,
          0.0,
          0.26,
          119.44,
          0.0,
          0.000310544,
          0.0,
          0.0,
          0.0
        ],
        [
          "אמות ד' מוגבל אנליסט 19.12.19- אמות השקעות בע\"מ",
          1133149,
          "TASE",
          "אחר",
          520026683,
          "נדל\"ן ובינוי",
          "AA.IL",
          "S&P מעלות",
          "19/12/17",
          "",
          "שקל חדש",
          3.2,
          0.0,
          209000.0,
          112.5,
          0.0,
          235.125,
          0.0,
          0.43,
          0.23
        ],
        [
          "חשמל 27- חברת החשמל לישראל בע\"מ",
          6000210,
          "TASE",
          "אחר",
          520000472,
          "שירותים",
          "Aa2.IL",
          "מידרוג",
          "18/01/18",
          7.91,
          "שקל חדש",
          3.85,
          0.02,
          885846.76,
          122.89,
          0.0,
          1088.617083364,
          0.03,
          2.0,
          1.05
        ],
        [
          "חשמל אגח 29- חברת החשמל לישראל בע\"מ",
          6000236,
          "TASE",
          "אחר",
          520000472,
          "חשמל",
          "Aa2.IL",
          "מידרוג",
          "24/10/17",
          6.11,
          "שקל חדש",
          4.5,
          0.01,
          337000.0,
          124.25,
          0.0,
          418.7225,
          0.01,
          0.77,
          0.4
        ],
        [
          "לאומי התח נד401- בנק לאומי לישראל בע\"מ",
          6040380,
          "TASE",
          "אחר",
          520018078,
          "בנקים",
          "AA.IL",
          "S&P מעלות",
          "10/07/18",
          4.65,
          "שקל חדש",
          1.64,
          0.01,
          5.0,
          5085000.0,
          0.0,
          254.25,
          0.04,
          0.47,
          0.25
        ],
        [
          "לאומי שה נד 200- בנק לאומי לישראל בע\"מ",
          6040141,
          "TASE",
          "אחר",
          520018078,
          "בנקים",
          "AA.IL",
          "S&P מעלות",
          "18/01/18",
          2.25,
          "שקל חדש",
          4.0,
          0.0,
          13029.0,
          119.89,
          0.0,
          15.6204681,
          0.0,
          0.03,
          0.02
        ],
        [
          "נתיבי גז אגח ד- נתיבי הגז הטבעי לישראל בע\"מ",
          1147503,
          "TASE",
          "אחר",
          1418,
          "חיפושי נפט וגז",
          "AA.IL",
          "S&P מעלות",
          "07/06/18",
          9.93,
          "שקל חדש",
          2.95,
          1.49,
          210000.0,
          111.5,
          0.0,
          234.15,
          0.02,
          0.43,
          0.23
        ],
        [
          "שופרסל אג\"ח ו'- שופרסל בע\"מ",
          7770217,
          "TASE",
          "אחר",
          520022732,
          "מזון",
          "AA.IL",
          "S&P מעלות",
          "10/07/18",
          5.55,
          "שקל חדש",
          4.3,
          0.01,
          210553.0,
          117.85,
          9.07048,
          257.2071905,
          0.02,
          0.47,
          0.25
        ],
        [
          "אדמה אגח ב- אדמה פתרונות לחקלאות בע\"מ",
          1110915,
          "TASE",
          "אחר",
          520043605,
          "כימיה, גומי ופלסטיק",
          "AA-.IL",
          "S&P מעלות",
          "06/10/16",
          8.19,
          "שקל חדש",
          5.15,
          0.03,
          672374.0,
          150.73,
          0.0,
          1013.4693302,
          0.02,
          1.86,
          0.98
        ],
        [
          "ביג אג'ח ט' 2018/2026 %1.95- ביג מרכזי קניות בע\"מ",
          1141050,
          "TASE",
          "אחר",
          513623314,
          "נדל\"ן ובינוי",
          "AA-.IL",
          "S&P מעלות",
          "23/07/17",
          5.69,
          "שקל חדש",
          1.95,
          0.02,
          548072.0,
          103.8,
          0.0,
          568.898736,
          0.08,
          1.05,
          0.55
        ],
        [
          "בראק אן וי אגחב- בראק קפיטל פרופרטיז אן וי",
          1128347,
          "TASE",
          "אחר",
          1560,
          "נדל\"ן ובינוי",
          "AA-.IL",
          "S&P מעלות",
          "03/08/17",
          3.71,
          "שקל חדש",
          3.29,
          0.01,
          0.34,
          112.7,
          0.0,
          0.00038318,
          0.0,
          0.0,
          0.0
        ],
        [
          "בראק אן וי אגחג- בראק קפיטל פרופרטיז אן וי",
          1133040,
          "TASE",
          "אחר",
          1560,
          "נדל\"ן ובינוי",
          "AA-.IL",
          "S&P מעלות",
          "22/08/16",
          5.95,
          "שקל חדש",
          3.3,
          0.01,
          0.52,
          112.07,
          0.0,
          0.000582764,
          0.0,
          0.0,
          0.0
        ],
        [
          "גזית גלוב אגחיא- גזית-גלוב בע\"מ",
          1260546,
          "TASE",
          "אחר",
          520033234,
          "נדל\"ן ובינוי",
          "AA-.IL",
          "S&P מעלות",
          "08/11/16",
          4.13,
          "שקל חדש",
          5.35,
          0.01,
          336601.8,
          121.68,
          49.19187,
          458.76894024,
          0.01,
          0.84,
          0.44
        ],
        [
          "גזית גלוב אגחיב- גזית-גלוב בע\"מ",
          1260603,
          "TASE",
          "אחר",
          520033234,
          "נדל\"ן ובינוי",
          "AA-.IL",
          "S&P מעלות",
          "27/12/17",
          6.41,
          "שקל חדש",
          4.0,
          0.02,
          945183.0,
          112.32,
          0.0,
          1061.6295456,
          0.03,
          1.95,
          1.03
        ],
        [
          "גזית גלוב אגחיג- גזית-גלוב בע\"מ",
          1260652,
          "TASE",
          "אחר",
          520033234,
          "נדל\"ן ובינוי",
          "AA-.IL",
          "S&P מעלות",
          "18/02/18",
          6.7,
          "שקל חדש",
          2.78,
          0.03,
          500000.0,
          104.02,
          0.0,
          520.1,
          0.04,
          0.96,
          0.5
        ],
        [
          "דיסק מנ שה נד 1- דיסקונט מנפיקים בע\"מ",
          7480098,
          "TASE",
          "אחר",
          520029935,
          "בנקים",
          "AA-.IL",
          "S&P מעלות",
          "09/01/17",
          1.49,
          "שקל חדש",
          6.4,
          0.0,
          319481.0,
          126.64,
          0.0,
          404.5907384,
          0.03,
          0.74,
          0.39
        ],
        [
          "דקסה הנפ נדח יג- דקסיה ישראל הנפקות בע\"מ",
          1125194,
          "TASE",
          "אחר",
          513704304,
          "בנקים",
          "AA-.IL",
          "S&P מעלות",
          "30/09/14",
          0.26,
          "שקל חדש",
          4.85,
          0.01,
          1017.0,
          108.32,
          0.0,
          1.1016144,
          0.0,
          0.0,
          0.0
        ],
        [
          "ישרס יג- ישרס חברה להשקעות בע\"מ",
          6130181,
          "TASE",
          "אחר",
          520017807,
          "נדל\"ן ובינוי",
          "AA-.IL",
          "S&P מעלות",
          "31/01/17",
          3.18,
          "שקל חדש",
          3.48,
          0.01,
          169465.66,
          109.89,
          0.0,
          186.225813774,
          0.03,
          0.34,
          0.18
        ],
        [
          "כללביט אגח ג- כללביט מימון בע\"מ",
          1120120,
          "TASE",
          "אחר",
          513754069,
          "ביטוח",
          "AA-.IL",
          "S&P מעלות",
          "18/01/18",
          2.72,
          "שקל חדש",
          3.75,
          0.0,
          648822.0,
          119.58,
          0.0,
          775.8613476,
          0.08,
          1.43,
          0.75
        ],
        [
          "מליסרון אגח ו- מליסרון בע\"מ",
          3230125,
          "TASE",
          "אחר",
          520037789,
          "נדל\"ן ובינוי",
          "AA-.IL",
          "S&P מעלות",
          "13/08/15",
          2.43,
          "שקל חדש",
          4.9,
          0.0,
          211273.09,
          117.47,
          0.0,
          248.182498823,
          0.03,
          0.46,
          0.24
        ],
        [
          "מליסרון אגח יא- מליסרון בע\"מ",
          3230208,
          "TASE",
          "אחר",
          520037789,
          "נדל\"ן ובינוי",
          "AA-.IL",
          "S&P מעלות",
          "17/01/16",
          5.87,
          "שקל חדש",
          2.3,
          0.02,
          292894.43,
          105.3,
          0.0,
          308.41783479,
          0.02,
          0.57,
          0.3
        ],
        [
          "מליסרון אגח יג- מליסרון בע\"מ",
          3230224,
          "TASE",
          "אחר",
          520037789,
          "נדל\"ן ובינוי",
          "AA-.IL",
          "S&P מעלות",
          "27/03/17",
          2.31,
          "שקל חדש",
          5.85,
          0.0,
          484597.65,
          125.02,
          0.0,
          605.84398203,
          0.04,
          1.11,
          0.59
        ],
        [
          "סלע קפיטל נדל\"ן ג- סלע קפיטל נדל\"ן בע\"מ",
          1138973,
          "TASE",
          "אחר",
          513992529,
          "נדל\"ן ובינוי",
          "Aa3.IL",
          "מידרוג",
          "19/07/17",
          6.9,
          "שקל חדש",
          1.96,
          0.02,
          0.35,
          102.53,
          0.0,
          0.000358855,
          0.0,
          0.0,
          0.0
        ],
        [
          "פועלים הנ הת יח- הפועלים הנפקות בע\"מ",
          1940600,
          "TASE",
          "אחר",
          520032640,
          "בנקים",
          "Aa3.IL",
          "מידרוג",
          "19/07/18",
          4.46,
          "שקל חדש",
          1.42,
          0.01,
          5.0,
          5070000.0,
          0.0,
          253.5,
          0.02,
          0.47,
          0.25
        ],
        [
          "פז נפט אגח ז- פז חברת הנפט בע\"מ",
          1142595,
          "TASE",
          "אחר",
          510216054,
          "חיפושי נפט וגז",
          "AA-.IL",
          "S&P מעלות",
          "14/12/17",
          6.84,
          "שקל חדש",
          1.23,
          0.01,
          370000.0,
          100.07,
          0.0,
          370.259,
          0.03,
          0.68,
          0.36
        ],
        [
          "פז נפט ו- פז חברת הנפט בע\"מ",
          1139542,
          "TASE",
          "אחר",
          510216054,
          "חיפושי נפט וגז",
          "AA-.IL",
          "S&P מעלות",
          "01/12/16",
          4.94,
          "שקל חדש",
          1.94,
          0.01,
          291698.52,
          106.94,
          0.0,
          311.942397288,
          0.04,
          0.57,
          0.3
        ],
        [
          "איידיאו אגח ח- איי.די.או. גרופ בע\"מ",
          5050265,
          "TASE",
          "אחר",
          520039066,
          "נדל\"ן ובינוי",
          "A+.IL",
          "S&P מעלות",
          "13/02/17",
          5.38,
          "שקל חדש",
          2.5,
          0.02,
          337335.0,
          106.8,
          0.0,
          360.27378,
          0.09,
          0.66,
          0.35
        ],
        [
          "בינל הנפק התחכד- הבינלאומי הראשון הנפקות בע\"מ",
          1151000,
          "TASE",
          "אחר",
          513141879,
          "בנקים",
          "A+.IL",
          "S&P מעלות",
          "15/07/18",
          5.48,
          "שקל חדש",
          2.2,
          0.02,
          4.0,
          5177777.0,
          0.0,
          207.11108,
          0.08,
          0.38,
          0.2
        ],
        [
          "דרבן אגח ד- דרבן השקעות בע\"מ",
          4110094,
          "TASE",
          "אחר",
          520038902,
          "נדל\"ן ובינוי",
          "A1.IL",
          "מידרוג",
          "17/12/17",
          1.74,
          "שקל חדש",
          4.6,
          0.0,
          98999.9,
          131.73,
          0.0,
          130.41256827,
          0.03,
          0.24,
          0.13
        ],
        [
          "יוניברסל מוטורס א- יוניברסל מוטורס ישראל בע\"מ",
          1141639,
          "TASE",
          "אחר",
          511809071,
          "מסחר",
          "A+.IL",
          "S&P מעלות",
          "10/09/17",
          2.42,
          "שקל חדש",
          2.65,
          0.01,
          416736.49,
          104.97,
          0.0,
          437.448293553,
          0.06,
          0.8,
          0.42
        ],
        [
          "ירושליםהנפ אגחט- ירושלים מימון והנפקות (2005) בע\"מ",
          1127422,
          "TASE",
          "אחר",
          513682146,
          "בנקים",
          "A+.IL",
          "S&P מעלות",
          "01/11/17",
          1.74,
          "שקל חדש",
          2.0,
          0.0,
          184879.2,
          107.21,
          0.0,
          198.20899032,
          0.03,
          0.36,
          0.19
        ],
        [
          "מבני תעשיה יז- מבני תעשיה בע\"מ",
          2260446,
          "TASE",
          "אחר",
          520024126,
          "נדל\"ן ובינוי",
          "A+.IL",
          "S&P מעלות",
          "22/02/17",
          5.19,
          "שקל חדש",
          3.7,
          0.02,
          198671.7,
          112.06,
          0.0,
          222.63150702,
          0.03,
          0.41,
          0.22
        ],
        [
          "מזרח טפחות שה א- בנק מזרחי טפחות בע\"מ",
          6950083,
          "TASE",
          "אחר",
          520000522,
          "בנקים",
          "A+.IL",
          "S&P מעלות",
          "18/01/18",
          3.07,
          "שקל חדש",
          4.5,
          0.01,
          681370.0,
          135.67,
          9.26067,
          933.675349,
          0.04,
          1.72,
          0.9
        ],
        [
          "נורסטאר אגח ט- נורסטאר החזקות אינק (חברה זרה)",
          7230303,
          "TASE",
          "אחר",
          723,
          "נדל\"ן ובינוי",
          "A+.IL",
          "S&P מעלות",
          "28/01/16",
          1.14,
          "שקל חדש",
          4.7,
          0.01,
          0.59,
          115.97,
          0.0,
          0.000684223,
          0.0,
          0.0,
          0.0
        ],
        [
          "נורסטאר אגח י- נורסטאר החזקות אינק (חברה זרה)",
          7230345,
          "TASE",
          "אחר",
          723,
          "נדל\"ן ובינוי",
          "A+.IL",
          "S&P מעלות",
          "03/01/16",
          2.44,
          "שקל חדש",
          4.42,
          0.01,
          165101.0,
          110.55,
          3.72114,
          186.2402955,
          0.02,
          0.34,
          0.18
        ],
        [
          "נורסטאר אגח יא- נורסטאר החזקות אינק (חברה זרה)",
          7230352,
          "TASE",
          "אחר",
          723,
          "נדל\"ן ובינוי",
          "A+.IL",
          "S&P מעלות",
          "14/08/17",
          4.58,
          "שקל חדש",
          3.0,
          0.02,
          521703.0,
          104.67,
          7.94313,
          554.0096601,
          0.11,
          1.02,
          0.54
        ],
        [
          "סלקום אגח ו- סלקום ישראל בע\"מ",
          1125996,
          "TASE",
          "אחר",
          511930125,
          "תקשורת ומדיה",
          "A+.IL",
          "S&P מעלות",
          "20/01/15",
          0.77,
          "שקל חדש",
          4.6,
          0.0,
          0.33,
          108.23,
          0.0,
          0.000357159,
          0.0,
          0.0,
          0.0
        ],
        [
          "פתאל החז אגח א- פתאל החזקות",
          1143437,
          "TASE",
          "אחר",
          512607888,
          "שירותים",
          "A1.IL",
          "מידרוג",
          "27/02/18",
          2.66,
          "שקל חדש",
          3.82,
          0.01,
          120000.05,
          110.0,
          0.0,
          132.000055,
          0.13,
          0.24,
          0.13
        ],
        [
          "רבוע נדלן אגח ד- רבוע כחול נדל\"ן בע\"מ",
          1119999,
          "TASE",
          "אחר",
          513765859,
          "נדל\"ן ובינוי",
          "A+.IL",
          "S&P מעלות",
          "19/07/16",
          1.23,
          "שקל חדש",
          4.5,
          0.0,
          85014.5,
          115.48,
          0.0,
          98.1747446,
          0.02,
          0.18,
          0.09
        ],
        [
          "רבוע נדלן אגח ה- רבוע כחול נדל\"ן בע\"מ",
          1130467,
          "TASE",
          "אחר",
          513765859,
          "נדל\"ן ובינוי",
          "A+.IL",
          "S&P מעלות",
          "30/11/16",
          3.38,
          "שקל חדש",
          3.3,
          0.01,
          309610.45,
          109.38,
          0.0,
          338.65191021,
          0.05,
          0.62,
          0.33
        ],
        [
          "רבוע נדלן אגח ו- רבוע כחול נדל\"ן בע\"מ",
          1140607,
          "TASE",
          "אחר",
          513765859,
          "נדל\"ן ובינוי",
          "A+.IL",
          "S&P מעלות",
          "11/01/18",
          5.61,
          "שקל חדש",
          2.15,
          0.02,
          350000.0,
          102.07,
          0.0,
          357.245,
          0.06,
          0.66,
          0.35
        ],
        [
          "אגוד הנ שה נד 1- אגוד הנפקות בע\"מ",
          1115278,
          "TASE",
          "אחר",
          513668277,
          "בנקים",
          "A2.IL",
          "מידרוג",
          "25/09/17",
          1.87,
          "שקל חדש",
          5.3,
          0.0,
          309528.0,
          120.78,
          0.0,
          373.8479184,
          0.12,
          0.69,
          0.36
        ],
        [
          "אלרוב נדלן אגחב- אלרוב נדל\"ן ומלונאות בע\"מ",
          3870094,
          "TASE",
          "אחר",
          520038894,
          "נדל\"ן ובינוי",
          "A2.IL",
          "מידרוג",
          "03/01/16",
          1.31,
          "שקל חדש",
          4.8,
          0.0,
          75205.34,
          109.35,
          0.0,
          82.23703929,
          0.04,
          0.15,
          0.08
        ],
        [
          "אלרוב נדלן אגחד- אלרוב נדל\"ן ומלונאות בע\"מ",
          3870128,
          "TASE",
          "אחר",
          520038894,
          "אחר",
          "A2.IL",
          "מידרוג",
          "10/01/17",
          3.39,
          "שקל חדש",
          2.4,
          0.01,
          240000.0,
          105.83,
          0.0,
          253.992,
          0.04,
          0.47,
          0.25
        ],
        [
          "אשטרום נכס10- אשטרום נכסים בע\"מ",
          2510204,
          "TASE",
          "אחר",
          520036617,
          "נדל\"ן ובינוי",
          "A.IL",
          "S&P מעלות",
          "19/07/17",
          5.23,
          "שקל חדש",
          3.06,
          0.02,
          468150.0,
          107.72,
          0.0,
          504.29118,
          0.16,
          0.93,
          0.49
        ],
        [
          "דיסקונט שה א- בנק דיסקונט לישראל בע\"מ",
          6910095,
          "TASE",
          "אחר",
          520007030,
          "בנקים",
          "A.IL",
          "S&P מעלות",
          "03/05/17",
          3.05,
          "שקל חדש",
          5.1,
          0.01,
          878747.0,
          138.74,
          13.56202,
          1232.7356078,
          0.08,
          2.27,
          1.19
        ],
        [
          "דלק קב אגח יג- קבוצת דלק בע\"מ",
          1105543,
          "TASE",
          "אחר",
          520044322,
          "השקעה ואחזקות",
          "A.IL",
          "S&P מעלות",
          "18/01/18",
          1.72,
          "שקל חדש",
          4.6,
          0.01,
          53823.0,
          130.03,
          1.50504,
          71.4910869,
          0.01,
          0.13,
          0.07
        ],
        [
          "דלק קב אגח יח- קבוצת דלק בע\"מ",
          1115823,
          "TASE",
          "אחר",
          520044322,
          "השקעה ואחזקות",
          "A2.IL",
          "מידרוג",
          "25/01/17",
          2.42,
          "שקל חדש",
          6.1,
          0.01,
          224630.02,
          125.62,
          0.0,
          282.180231124,
          0.03,
          0.52,
          0.27
        ],
        [
          "דלק קב אגח יט- קבוצת דלק בע\"מ",
          1121326,
          "TASE",
          "אחר",
          520044322,
          "השקעה ואחזקות",
          "A2.IL",
          "מידרוג",
          "18/01/18",
          2.48,
          "שקל חדש",
          4.65,
          0.01,
          41623.0,
          118.36,
          0.0,
          49.2649828,
          0.01,
          0.09,
          0.05
        ],
        [
          "חברה לישראלאגח7- החברה לישראל בע\"מ",
          5760160,
          "TASE",
          "אחר",
          520028010,
          "השקעה ואחזקות",
          "A.IL",
          "S&P מעלות",
          "15/03/17",
          1.43,
          "שקל חדש",
          4.95,
          0.0,
          160093.8,
          130.1,
          0.0,
          208.2820338,
          0.01,
          0.38,
          0.2
        ],
        [
          "מגה אור אגח ו- מגה אור החזקות בע\"מ",
          1138668,
          "TASE",
          "אחר",
          513257873,
          "נדל\"ן ובינוי",
          "A.IL",
          "S&P מעלות",
          "18/12/16",
          4.88,
          "שקל חדש",
          2.05,
          0.02,
          145445.0,
          104.55,
          0.0,
          152.0627475,
          0.03,
          0.28,
          0.15
        ],
        [
          "שכון ובי אגח 6- שיכון ובינוי בע\"מ",
          1129733,
          "TASE",
          "אחר",
          520036104,
          "נדל\"ן ובינוי",
          "A.IL",
          "S&P מעלות",
          "03/03/16",
          4.12,
          "שקל חדש",
          4.34,
          0.02,
          349142.14,
          108.3,
          7.59051,
          385.71144762,
          0.02,
          0.71,
          0.37
        ],
        [
          "שכון ובי אגח 8- שיכון ובינוי בע\"מ",
          1135888,
          "TASE",
          "אחר",
          520036104,
          "נדל\"ן ובינוי",
          "A.IL",
          "S&P מעלות",
          "26/04/18",
          6.44,
          "שקל חדש",
          3.9,
          0.04,
          808396.72,
          105.01,
          0.0,
          848.897395672,
          0.04,
          1.56,
          0.82
        ],
        [
          "אגוד הנפקות כ ש\"ה- אגוד הנפקות בע\"מ",
          1139153,
          "TASE",
          "אחר",
          513668277,
          "בנקים",
          "A3.IL",
          "מידרוג",
          "12/09/16",
          2.88,
          "שקל חדש",
          2.85,
          0.02,
          3.0,
          5200000.0,
          0.0,
          156.0,
          0.07,
          0.29,
          0.15
        ],
        [
          "אדגר אגח ט- אדגר השקעות ופיתוח בע\"מ",
          1820190,
          "TASE",
          "אחר",
          520035171,
          "נדל\"ן ובינוי",
          "A3.IL",
          "מידרוג",
          "12/09/16",
          4.32,
          "שקל חדש",
          4.65,
          0.02,
          172000.0,
          113.61,
          0.0,
          195.4092,
          0.02,
          0.36,
          0.19
        ],
        [
          "אלבר אגח טז- אלבר שירותי מימונית בע\"מ",
          1139823,
          "TASE",
          "אחר",
          512025891,
          "שירותים",
          "A3.IL",
          "מידרוג",
          "01/08/18",
          2.88,
          "שקל חדש",
          2.25,
          0.02,
          256081.66,
          102.88,
          0.0,
          263.456811808,
          0.06,
          0.48,
          0.25
        ],
        [
          "אספן גרופ ו- אספן גרופ בע\"מ",
          3130291,
          "TASE",
          "אחר",
          520037540,
          "נדל\"ן ובינוי",
          "A3.IL",
          "מידרוג",
          "29/01/17",
          3.09,
          "שקל חדש",
          3.9,
          0.02,
          256581.8,
          107.45,
          0.0,
          275.6971441,
          0.06,
          0.51,
          0.27
        ],
        [
          "אפריקה נכס אגחו- אפריקה ישראל נכסים בע\"מ",
          1129550,
          "TASE",
          "אחר",
          510560188,
          "נדל\"ן ובינוי",
          "A3.IL",
          "מידרוג",
          "30/09/14",
          1.33,
          "שקל חדש",
          4.8,
          0.0,
          111619.95,
          107.73,
          0.0,
          120.248172135,
          0.06,
          0.22,
          0.12
        ],
        [
          "אפריקה נכס אגחז- אפריקה ישראל נכסים בע\"מ",
          1132232,
          "TASE",
          "אחר",
          510560188,
          "נדל\"ן ובינוי",
          "A3.IL",
          "מידרוג",
          "26/12/17",
          3.36,
          "שקל חדש",
          3.7,
          0.02,
          476259.0,
          108.86,
          0.0,
          518.4555474,
          0.06,
          0.95,
          0.5
        ],
        [
          "אפריקה נכס אגחח- אפריקה ישראל נכסים בע\"מ",
          1142231,
          "TASE",
          "אחר",
          510560188,
          "נדל\"ן ובינוי",
          "A3.IL",
          "מידרוג",
          "04/01/18",
          6.05,
          "שקל חדש",
          2.57,
          0.03,
          929753.0,
          99.2,
          0.0,
          922.314976,
          0.08,
          1.7,
          0.89
        ],
        [
          "ירושליםהנפ נד10- ירושלים מימון והנפקות (2005) בע\"מ",
          1127414,
          "TASE",
          "אחר",
          513682146,
          "בנקים",
          "A-.IL",
          "S&P מעלות",
          "25/09/17",
          1.73,
          "שקל חדש",
          2.4,
          0.0,
          452651.0,
          106.54,
          0.0,
          482.2543754,
          0.35,
          0.89,
          0.47
        ],
        [
          "לוזון קבוצה ז- קבוצת עמוס לוזון יזמות ואנרגיה בע\"מ",
          4730149,
          "TASE",
          "אחר",
          520039660,
          "נדל\"ן ובינוי",
          "Baa2.IL",
          "מידרוג",
          "30/09/14",
          2.19,
          "שקל חדש",
          3.65,
          0.09,
          221172.7,
          89.92,
          35.89317,
          234.77166184,
          0.29,
          0.43,
          0.23
        ],
        [
          "אידיבי פת אגח ט- אידיבי חברה לפתוח בע\"מ",
          7980154,
          "TASE",
          "אחר",
          520032285,
          "השקעה ואחזקות",
          "BBB-.IL",
          "S&P מעלות",
          "23/07/17",
          3.93,
          "שקל חדש",
          4.95,
          0.12,
          205658.0,
          95.5,
          0.0,
          196.40339,
          0.02,
          0.36,
          0.19
        ],
        [
          "אינטרנט זהב ד- אינטרנט גולד - קווי זהב בע\"מ",
          1131614,
          "TASE",
          "אחר",
          520044264,
          "תקשורת ומדיה",
          "Baa3.IL",
          "מידרוג",
          "25/12/17",
          2.44,
          "שקל חדש",
          6.0,
          0.07,
          488791.8,
          99.72,
          0.0,
          487.42318296,
          0.07,
          0.9,
          0.47
        ],
        [
          "אפריקה אגח כו- אפריקה-ישראל להשקעות בע\"מ",
          6110365,
          "TASE",
          "אחר",
          520005067,
          "נדל\"ן ובינוי",
          "NR",
          "לא מדורג",
          "03/01/16",
          1.7,
          "שקל חדש",
          7.5,
          0.3,
          0.16,
          85.74,
          0.0,
          0.000137184,
          0.0,
          0.0,
          0.0
        ],
        [
          "נאוסיטי   אגח א- קבוצת נאוסיטי להשקעות ואחזקות בע\"מ",
          1102375,
          "TASE",
          "אחר",
          513904367,
          "נדל\"ן ובינוי",
          "NR",
          "לא מדורג",
          "30/09/14",
          0.91,
          "שקל חדש",
          6.75,
          6.32,
          20405.44,
          122.35,
          0.0,
          24.96605584,
          0.3,
          0.05,
          0.02
        ],
        [
          "צור אגח י- צור שמיר אחזקות בע\"מ",
          7300171,
          "TASE",
          "אחר",
          520025586,
          "השקעה ואחזקות",
          "NR",
          "לא מדורג",
          "28/06/18",
          5.98,
          "שקל חדש",
          3.7,
          0.03,
          150000.0,
          105.04,
          0.0,
          157.56,
          0.03,
          0.29,
          0.15
        ],
        [
          "בזק 9- בזק החברה הישראלית לתקשורת בע\"מ",
          2300176,
          "TASE",
          "אחר",
          520031931,
          "תקשורת ומדיה",
          "AA.IL",
          "S&P מעלות",
          "25/09/17",
          5.38,
          "שקל חדש",
          3.65,
          0.03,
          353199.0,
          106.22,
          0.0,
          375.1679778,
          0.02,
          0.69,
          0.36
        ],
        [
          "חשמל 26- חברת החשמל לישראל בע\"מ",
          6000202,
          "TASE",
          "אחר",
          520000472,
          "חשמל",
          "Aa2.IL",
          "מידרוג",
          "25/07/18",
          3.48,
          "שקל חדש",
          4.8,
          0.02,
          300880.28,
          113.88,
          0.0,
          342.642462864,
          0.01,
          0.63,
          0.33
        ],
        [
          "שופרסל אגח ה- שופרסל בע\"מ",
          7770209,
          "TASE",
          "אחר",
          520022732,
          "מזון",
          "AA.IL",
          "S&P מעלות",
          "25/01/18",
          5.39,
          "שקל חדש",
          5.09,
          0.03,
          457628.43,
          113.16,
          67.01343,
          584.865761388,
          0.04,
          1.08,
          0.57
        ],
        [
          "אלוני חץ ט- אלוני-חץ נכסים והשקעות בע\"מ",
          3900354,
          "TASE",
          "אחר",
          520038506,
          "נדל\"ן ובינוי",
          "AA-.IL",
          "S&P מעלות",
          "09/07/18",
          4.79,
          "שקל חדש",
          3.85,
          0.03,
          215750.0,
          107.32,
          0.0,
          231.5429,
          0.02,
          0.43,
          0.22
        ],
        [
          "דה זראסאי גרופ ג- דה זראסאי גרופ לטד",
          1137975,
          "TASE",
          "אחר",
          1604,
          "נדל\"ן ובינוי",
          "Aa3.IL",
          "מידרוג",
          "07/11/17",
          4.29,
          "שקל חדש",
          4.35,
          0.04,
          1217785.0,
          103.32,
          0.0,
          1258.215462,
          0.06,
          2.31,
          1.22
        ],
        [
          "וורטון אגח א- וורטון פרופרטיז (בי.וי.איי) לימיטד",
          1140169,
          "TASE",
          "אחר",
          1645,
          "נדל\"ן ובינוי",
          "AA-.IL",
          "S&P מעלות",
          "25/09/17",
          3.13,
          "שקל חדש",
          3.9,
          0.04,
          318950.0,
          98.72,
          0.0,
          314.86744,
          0.04,
          0.58,
          0.3
        ],
        [
          "ישרס יד- ישרס חברה להשקעות בע\"מ",
          6130199,
          "TASE",
          "אחר",
          520017807,
          "נדל\"ן ובינוי",
          "AA-.IL",
          "S&P מעלות",
          "07/08/18",
          4.35,
          "שקל חדש",
          5.05,
          0.03,
          32916.0,
          110.34,
          0.0,
          36.3195144,
          0.01,
          0.07,
          0.04
        ],
        [
          "מגדל הון אגח ו- מגדל ביטוח גיוס הון בע\"מ",
          1142785,
          "TASE",
          "אחר",
          513230029,
          "ביטוח",
          "Aa3.IL",
          "מידרוג",
          "22/01/18",
          6.57,
          "שקל חדש",
          2.63,
          0.03,
          391654.0,
          99.56,
          0.0,
          389.9307224,
          0.03,
          0.72,
          0.38
        ],
        [
          "פז נפט אגח ג- פז חברת הנפט בע\"מ",
          1114073,
          "TASE",
          "אחר",
          510216054,
          "השקעה ואחזקות",
          "AA-.IL",
          "S&P מעלות",
          "24/07/18",
          0.65,
          "שקל חדש",
          2.3,
          0.01,
          272723.0,
          101.1,
          1.58558,
          277.308533,
          0.01,
          0.51,
          0.27
        ],
        [
          "קיי.בי.אס אגח א- קיי.בי.אס.אס.או.אר(בי.וי.איי)הולדינג אל.טי.די",
          1137918,
          "TASE",
          "אחר",
          1662,
          "Software & Services",
          "AA-.IL",
          "S&P מעלות",
          "29/11/17",
          2.3,
          "שקל חדש",
          4.25,
          0.04,
          395367.0,
          102.04,
          0.0,
          403.4324868,
          0.04,
          0.74,
          0.39
        ],
        [
          "קרסו מוטור א- קרסו מוטורס בע\"מ",
          1136464,
          "TASE",
          "אחר",
          514065283,
          "מסחר",
          "Aa3.IL",
          "מידרוג",
          "12/07/16",
          3.94,
          "שקל חדש",
          2.75,
          0.02,
          228707.02,
          102.38,
          0.0,
          234.150247076,
          0.05,
          0.43,
          0.23
        ],
        [
          "דמרי אגח ד- י.ח.דמרי בניה ופיתוח בע\"מ",
          1129667,
          "TASE",
          "אחר",
          511399388,
          "נדל\"ן ובינוי",
          "A1.IL",
          "מידרוג",
          "03/01/16",
          0.74,
          "שקל חדש",
          5.45,
          0.01,
          58134.08,
          104.5,
          0.0,
          60.7501136,
          0.12,
          0.11,
          0.06
        ],
        [
          "דמרי אגח ה- י.ח.דמרי בניה ופיתוח בע\"מ",
          1134261,
          "TASE",
          "אחר",
          511399388,
          "נדל\"ן ובינוי",
          "A1.IL",
          "מידרוג",
          "29/01/15",
          1.54,
          "שקל חדש",
          3.5,
          0.01,
          218.36,
          104.24,
          0.0,
          0.227618464,
          0.0,
          0.0,
          0.0
        ],
        [
          "דמרי אגח ח- י.ח.דמרי בניה ופיתוח בע\"מ",
          1153725,
          "TASE",
          "אחר",
          511399388,
          "נדל\"ן ובינוי",
          "A1.IL",
          "מידרוג",
          "19/08/18",
          4.86,
          "שקל חדש",
          4.17,
          3.82,
          59000.0,
          102.37,
          0.0,
          60.3983,
          0.03,
          0.11,
          0.06
        ],
        [
          "יוניברסל מוטורס ב- יוניברסל מוטורס ישראל בע\"מ",
          1141647,
          "TASE",
          "אחר",
          511809071,
          "מסחר",
          "A+.IL",
          "S&P מעלות",
          "26/07/18",
          2.38,
          "שקל חדש",
          3.4,
          0.02,
          311623.01,
          103.24,
          0.0,
          321.719595524,
          0.06,
          0.59,
          0.31
        ],
        [
          "ישרוטל א- ישרוטל בע\"מ",
          1139419,
          "TASE",
          "אחר",
          520042482,
          "מלונאות ותיירות",
          "A1.IL",
          "מידרוג",
          "24/04/17",
          3.34,
          "שקל חדש",
          2.45,
          0.02,
          322968.0,
          103.42,
          0.0,
          334.0135056,
          0.19,
          0.61,
          0.32
        ],
        [
          "לייטסטון אגח א- לייטסטון אנטרפרייזס לימיטד",
          1133891,
          "TASE",
          "אחר",
          1630,
          "נדל\"ן ובינוי",
          "A+.IL",
          "S&P מעלות",
          "27/12/17",
          2.85,
          "שקל חדש",
          6.35,
          0.04,
          533394.76,
          109.36,
          0.0,
          583.320509536,
          0.07,
          1.07,
          0.56
        ],
        [
          "מבני תעשיה טו- מבני תעשיה בע\"מ",
          2260420,
          "TASE",
          "אחר",
          520024126,
          "נדל\"ן ובינוי",
          "A+.IL",
          "S&P מעלות",
          "18/02/15",
          2.84,
          "שקל חדש",
          5.74,
          0.02,
          0.01,
          110.69,
          0.0,
          1.1069e-05,
          0.0,
          0.0,
          0.0
        ],
        [
          "מויניאן א- מויניאן לימיטד",
          1135656,
          "TASE",
          "אחר",
          1643,
          "נדל\"ן ובינוי",
          "A1.IL",
          "מידרוג",
          "05/04/17",
          2.29,
          "שקל חדש",
          4.45,
          0.04,
          194976.9,
          103.07,
          0.0,
          200.96269083,
          0.02,
          0.37,
          0.19
        ],
        [
          "נכסים ובנ אגח ט- חברה לנכסים ולבנין בע\"מ",
          6990212,
          "TASE",
          "אחר",
          520025438,
          "נדל\"ן ובינוי",
          "A1.IL",
          "מידרוג",
          "25/07/18",
          5.89,
          "שקל חדש",
          3.95,
          0.04,
          254740.4,
          101.87,
          0.0,
          259.50404548,
          0.02,
          0.48,
          0.25
        ],
        [
          "סלקום אגח יב- סלקום ישראל בע\"מ",
          1143080,
          "TASE",
          "אחר",
          511930125,
          "תקשורת ומדיה",
          "A+.IL",
          "S&P מעלות",
          "24/01/18",
          6.29,
          "שקל חדש",
          2.5,
          0.04,
          179000.0,
          93.71,
          0.0,
          167.7409,
          0.04,
          0.31,
          0.16
        ],
        [
          "פתאל אירופה ג- פתאל נכסים(אירופה)בע\"מ",
          1141852,
          "TASE",
          "אחר",
          515328250,
          "נדל\"ן ובינוי",
          "A1.IL",
          "מידרוג",
          "26/07/18",
          5.53,
          "שקל חדש",
          2.65,
          0.04,
          236308.48,
          95.79,
          0.0,
          226.359892992,
          0.13,
          0.42,
          0.22
        ],
        [
          "שלמה החז אגח טו- ש.שלמה החזקות בע\"מ",
          1410273,
          "TASE",
          "אחר",
          520034372,
          "שירותים",
          "A1.IL",
          "מידרוג",
          "06/06/16",
          0.78,
          "שקל חדש",
          5.75,
          0.01,
          0.01,
          104.25,
          0.0,
          1.0425e-05,
          0.0,
          0.0,
          0.0
        ],
        [
          "אול-יר אגח ד",
          1141274,
          "TASE",
          "אחר",
          1631,
          "נדל\"ן ובינוי",
          "A2.IL",
          "מידרוג",
          "02/11/17",
          5.51,
          "שקל חדש",
          6.1,
          0.05,
          197000.0,
          93.25,
          0.0,
          183.7025,
          0.07,
          0.34,
          0.18
        ],
        [
          "אול-יר אגח ד- אול-יר הולדינגס לימיטד",
          1141274,
          "TASE",
          "אחר",
          1631,
          "נדל\"ן ובינוי",
          "A2.IL",
          "מידרוג",
          "30/07/17",
          4.92,
          "שקל חדש",
          6.1,
          0.08,
          1101766.0,
          93.25,
          0.0,
          1027.396795,
          0.22,
          1.89,
          0.99
        ],
        [
          "אפריקה מג אגח ד- אפריקה ישראל מגורים בע\"מ",
          1142645,
          "TASE",
          "אחר",
          520034760,
          "נדל\"ן ובינוי",
          "A2.IL",
          "מידרוג",
          "02/08/18",
          4.8,
          "שקל חדש",
          2.75,
          0.04,
          167731.0,
          95.32,
          2.3063,
          162.1874892,
          0.08,
          0.3,
          0.16
        ],
        [
          "אפריקה מגו ג- אפריקה ישראל מגורים בע\"מ",
          1135698,
          "TASE",
          "אחר",
          520034760,
          "נדל\"ן ובינוי",
          "A2.IL",
          "מידרוג",
          "31/07/18",
          2.45,
          "שקל חדש",
          3.9,
          0.02,
          18968.0,
          104.16,
          0.36988,
          20.1269488,
          0.01,
          0.04,
          0.02
        ],
        [
          "אשטרום נכ אגח 9- אשטרום נכסים בע\"מ",
          2510170,
          "TASE",
          "אחר",
          520036617,
          "נדל\"ן ובינוי",
          "A.IL",
          "S&P מעלות",
          "29/12/15",
          5.75,
          "שקל חדש",
          4.9,
          0.04,
          0.42,
          107.59,
          3e-05,
          0.000481878,
          0.0,
          0.0,
          0.0
        ],
        [
          "בי קומיוניק ג- בי קומיוניקיישנס בע\"מ",
          1139203,
          "TASE",
          "אחר",
          512832742,
          "תקשורת ומדיה",
          "A2.IL",
          "מידרוג",
          "08/08/18",
          4.87,
          "שקל חדש",
          3.6,
          0.05,
          191602.0,
          96.42,
          0.0,
          184.7426484,
          0.01,
          0.34,
          0.18
        ],
        [
          "דלק קב אגח לא- קבוצת דלק בע\"מ",
          1134790,
          "TASE",
          "אחר",
          520044322,
          "השקעה ואחזקות",
          "A.IL",
          "S&P מעלות",
          "18/01/18",
          4.17,
          "שקל חדש",
          4.3,
          0.04,
          663880.0,
          99.93,
          0.0,
          663.415284,
          0.02,
          1.22,
          0.64
        ],
        [
          "דלק קב אגח לד- קבוצת דלק בע\"מ",
          1143361,
          "TASE",
          "אחר",
          520044322,
          "השקעה ואחזקות",
          "A.IL",
          "S&P מעלות",
          "12/02/18",
          6.02,
          "שקל חדש",
          4.48,
          0.05,
          340000.0,
          96.74,
          0.0,
          328.916,
          0.07,
          0.6,
          0.32
        ],
        [
          "דלק קבוצה לב- קבוצת דלק בע\"מ",
          1138874,
          "TASE",
          "אחר",
          520044322,
          "השקעה ואחזקות",
          "A.IL",
          "S&P מעלות",
          "05/10/16",
          0.78,
          "שקל חדש",
          1.72,
          0.01,
          276221.0,
          100.9,
          0.0,
          278.706989,
          0.07,
          0.51,
          0.27
        ],
        [
          "דלק קבוצה לג",
          1138882,
          "TASE",
          "אחר",
          520044322,
          "השקעה ואחזקות",
          "A.IL",
          "S&P מעלות",
          "13/03/17",
          3.14,
          "שקל חדש",
          2.8,
          0.03,
          613245.0,
          98.8,
          0.0,
          605.88606,
          0.09,
          1.11,
          0.59
        ],
        [
          "ויקטורי אג\"ח א- ויקטורי רשת סופרמרקטים בע\"מ",
          1136126,
          "TASE",
          "אחר",
          514068980,
          "מסחר",
          "A2.IL",
          "מידרוג",
          "06/08/15",
          2.79,
          "שקל חדש",
          3.5,
          0.02,
          73916.88,
          103.7,
          0.0,
          76.65180456,
          0.1,
          0.14,
          0.07
        ],
        [
          "כלכלית ים אגחיג- כלכלית ירושלים בע\"מ",
          1980366,
          "TASE",
          "אחר",
          520017070,
          "נדל\"ן ובינוי",
          "A2.IL",
          "מידרוג",
          "29/02/16",
          2.38,
          "שקל חדש",
          5.0,
          0.02,
          0.24,
          108.64,
          0.0,
          0.000260736,
          0.0,
          0.0,
          0.0
        ],
        [
          "כנפיים    ז- כנפיים אחזקות בע\"מ",
          5430137,
          "TASE",
          "אחר",
          520040700,
          "שירותים",
          "A.IL",
          "S&P מעלות",
          "06/08/18",
          3.2,
          "שקל חדש",
          6.25,
          0.04,
          118689.21,
          107.31,
          24.10874,
          151.474131251,
          0.09,
          0.28,
          0.15
        ],
        [
          "מגדלי ים ב- מגדלי הים התיכון בע\"מ",
          1136803,
          "TASE",
          "אחר",
          512719485,
          "נדל\"ן ובינוי",
          "A2.IL",
          "מידרוג",
          "23/03/17",
          3.07,
          "שקל חדש",
          3.35,
          0.02,
          251380.0,
          104.5,
          4.21062,
          266.90272,
          0.08,
          0.49,
          0.26
        ],
        [
          "סטרווד ווסטאגחא- סטרווד ווסט לימיטד",
          1143544,
          "TASE",
          "אחר",
          1723,
          "נדל\"ן ובינוי",
          "A.IL",
          "S&P מעלות",
          "30/08/18",
          4.05,
          "שקל חדש",
          5.54,
          0.09,
          507291.0,
          90.66,
          0.0,
          459.9100206,
          0.06,
          0.85,
          0.44
        ],
        [
          "ספנסר אגח א- ספנסר אקוויטי גרופ לימיטד",
          1133800,
          "TASE",
          "אחר",
          1628,
          "נדל\"ן ובינוי",
          "A.IL",
          "S&P מעלות",
          "09/01/18",
          2.4,
          "שקל חדש",
          6.9,
          0.05,
          865587.97,
          108.6,
          0.0,
          940.02853542,
          0.17,
          1.73,
          0.91
        ],
        [
          "ספנסר אגח ב- ספנסר אקוויטי גרופ לימיטד",
          1139898,
          "TASE",
          "אחר",
          1628,
          "נדל\"ן ובינוי",
          "A.IL",
          "S&P מעלות",
          "28/02/18",
          4.19,
          "שקל חדש",
          5.15,
          0.07,
          394300.57,
          93.72,
          10.15324,
          379.691734204,
          0.1,
          0.7,
          0.37
        ],
        [
          "קופרליין אגח ב- קופרליין אמריקאס לימיטד",
          1140177,
          "TASE",
          "אחר",
          1865427,
          "נדל\"ן ובינוי",
          "A.IL",
          "S&P מעלות",
          "18/01/18",
          4.27,
          "שקל חדש",
          5.1,
          0.07,
          588439.8,
          93.1,
          15.00521,
          562.8426638,
          0.17,
          1.03,
          0.54
        ],
        [
          "או.פי.סי אנרגיה בע\"מ- או.פי.סי אנרגיה בע\"מ",
          1141589,
          "TASE",
          "אחר",
          514401702,
          "חשמל",
          "A-.IL",
          "S&P מעלות",
          "20/08/17",
          5.77,
          "שקל חדש",
          4.45,
          0.04,
          253795.0,
          105.57,
          0.0,
          267.9313815,
          0.08,
          0.49,
          0.26
        ],
        [
          "אלבר טו- אלבר שירותי מימונית בע\"מ",
          1138536,
          "TASE",
          "אחר",
          512025891,
          "שירותים",
          "A3.IL",
          "מידרוג",
          "26/06/17",
          2.51,
          "שקל חדש",
          3.0,
          0.03,
          184089.69,
          100.95,
          0.0,
          185.838542055,
          0.03,
          0.34,
          0.18
        ],
        [
          "אלבר יד- אלבר שירותי מימונית בע\"מ",
          1132562,
          "TASE",
          "אחר",
          512025891,
          "שירותים",
          "A3.IL",
          "מידרוג",
          "27/07/16",
          1.58,
          "שקל חדש",
          3.3,
          0.02,
          101229.65,
          101.86,
          0.0,
          103.11252149,
          0.02,
          0.19,
          0.1
        ],
        [
          "אמ.די.ג'י אגח ב- אמ.די.ג'י. ריאל אסטייט גלובל לימיטד",
          1140557,
          "TASE",
          "אחר",
          1632,
          "נדל\"ן ובינוי",
          "A3.IL",
          "מידרוג",
          "11/09/17",
          2.42,
          "שקל חדש",
          3.75,
          0.05,
          338347.35,
          98.45,
          0.0,
          333.102966075,
          0.13,
          0.61,
          0.32
        ],
        [
          "אמ.די.ג'י אגח ג- אמ.די.ג'י. ריאל אסטייט גלובל לימיטד",
          1142504,
          "TASE",
          "אחר",
          1632,
          "נדל\"ן ובינוי",
          "A3.IL",
          "מידרוג",
          "24/12/17",
          3.74,
          "שקל חדש",
          5.9,
          0.08,
          325082.46,
          94.35,
          0.0,
          306.71530101,
          0.1,
          0.56,
          0.3
        ],
        [
          "אקסטיל ב- אקסטל לימיטד",
          1135367,
          "TASE",
          "אחר",
          1622,
          "נדל\"ן ובינוי",
          "A3.IL",
          "מידרוג",
          "31/12/17",
          2.51,
          "שקל חדש",
          6.25,
          0.11,
          407414.0,
          91.69,
          0.0,
          373.5578966,
          0.07,
          0.69,
          0.36
        ],
        [
          "אקסטל אג\"ח א- אקסטל לימיטד",
          1132299,
          "TASE",
          "אחר",
          1622,
          "נדל\"ן ובינוי",
          "A3.IL",
          "מידרוג",
          "31/12/17",
          0.73,
          "שקל חדש",
          4.9,
          0.08,
          297099.0,
          99.06,
          0.0,
          294.3062694,
          0.03,
          0.54,
          0.28
        ],
        [
          "ארקו אגח ג",
          3100245,
          "TASE",
          "אחר",
          520037367,
          "השקעה ואחזקות",
          "A3.IL",
          "מידרוג",
          "03/07/18",
          "",
          "שקל חדש",
          4.85,
          0.0,
          157305.69,
          105.28,
          0.0,
          165.611430432,
          0.09,
          0.3,
          0.16
        ],
        [
          "ארקו אגח ג- ארקו החזקות בע\"מ",
          3100245,
          "TASE",
          "אחר",
          520037367,
          "השקעה ואחזקות",
          "A3.IL",
          "מידרוג",
          "03/07/17",
          3.61,
          "שקל חדש",
          4.85,
          0.04,
          96042.78,
          105.28,
          0.0,
          101.113838784,
          0.03,
          0.19,
          0.1
        ],
        [
          "סטרוברי אגח א- סטרוברי פילדס ריט לימיטד",
          1136951,
          "TASE",
          "אחר",
          1863501,
          "נדל\"ן ובינוי",
          "A-.IL",
          "S&P מעלות",
          "08/03/18",
          2.64,
          "שקל חדש",
          6.6,
          0.06,
          459113.83,
          102.67,
          0.0,
          471.372169261,
          0.18,
          0.87,
          0.46
        ],
        [
          "צ'וזן נכס אגח א- צ'וזן נכסים לימיטד",
          1141894,
          "TASE",
          "אחר",
          1698,
          "נדל\"ן ובינוי",
          "A-.IL",
          "S&P מעלות",
          "08/10/17",
          3.16,
          "שקל חדש",
          6.75,
          0.07,
          358928.0,
          99.72,
          12.11382,
          370.0368216,
          0.08,
          0.68,
          0.36
        ],
        [
          "שלמה נדלן ג- ש.י.ר שלמה נדל\"ן בע\"מ",
          1137439,
          "TASE",
          "אחר",
          513957472,
          "נדל\"ן ובינוי",
          "A3.IL",
          "מידרוג",
          "05/02/16",
          3.09,
          "שקל חדש",
          4.35,
          0.03,
          155600.02,
          103.69,
          0.0,
          161.341660738,
          0.04,
          0.3,
          0.16
        ],
        [
          "אופל בלאנס אגחג- אופל בלאנס השקעות בע\"מ",
          1140664,
          "TASE",
          "אחר",
          513734566,
          "שירותים פיננסיים",
          "Baa1.IL",
          "מידרוג",
          "01/01/18",
          1.31,
          "שקל חדש",
          2.5,
          0.03,
          296950.9,
          99.3,
          3.71189,
          298.5841337,
          0.5,
          0.55,
          0.29
        ],
        [
          "אורשי אגח א- אורשי ג.ש. בע\"מ",
          1141654,
          "TASE",
          "אחר",
          513547224,
          "שירותים פיננסיים",
          "Baa1.IL",
          "מידרוג",
          "09/11/17",
          0.99,
          "שקל חדש",
          3.04,
          0.02,
          291987.0,
          101.45,
          0.0,
          296.2208115,
          0.52,
          0.54,
          0.29
        ],
        [
          "אלדן א 4.3%- אלדן תחבורה בע\"מ",
          1134840,
          "TASE",
          "אחר",
          510454333,
          "שירותים",
          "Baa1.IL",
          "מידרוג",
          "18/08/16",
          1.38,
          "שקל חדש",
          4.3,
          0.03,
          130818.6,
          101.96,
          0.0,
          133.38264456,
          0.04,
          0.25,
          0.13
        ],
        [
          "אלדן תחבו אגח ג- אלדן תחבורה בע\"מ",
          1140813,
          "TASE",
          "אחר",
          510454333,
          "שירותים",
          "Baa1.IL",
          "מידרוג",
          "02/08/17",
          1.96,
          "שקל חדש",
          3.7,
          0.04,
          282194.65,
          100.99,
          0.0,
          284.988377035,
          0.09,
          0.52,
          0.28
        ],
        [
          "אלומיי א- אלומיי קפיטל בע\"מ",
          1130947,
          "TASE",
          "אחר",
          520039868,
          "Technology Hardware & Equipment",
          "BBB+.IL",
          "S&P מעלות",
          "29/12/14",
          2.57,
          "שקל חדש",
          4.6,
          0.03,
          183606.33,
          104.5,
          0.0,
          191.86861485,
          0.15,
          0.35,
          0.19
        ],
        [
          "אלומיי אגח ב- אלומיי קפיטל בע\"מ",
          1140326,
          "TASE",
          "אחר",
          520039868,
          "Technology Hardware & Equipment",
          "BBB+.IL",
          "S&P מעלות",
          "14/03/17",
          3.19,
          "שקל חדש",
          3.69,
          0.04,
          92027.0,
          100.1,
          0.0,
          92.119027,
          0.07,
          0.17,
          0.09
        ],
        [
          "אלון רבוע אגח ד- רבוע כחול נדל\"ן בע\"מ",
          1139583,
          "TASE",
          "אחר",
          513765859,
          "מסחר",
          "Baa1.IL",
          "מידרוג",
          "18/12/17",
          3.7,
          "שקל חדש",
          4.6,
          0.05,
          934791.0,
          99.56,
          0.0,
          930.6779196,
          0.1,
          1.71,
          0.9
        ],
        [
          "דיסק השק אגח י- חברת השקעות דיסקונט בע\"מ",
          6390348,
          "TASE",
          "אחר",
          520023896,
          "השקעה ואחזקות",
          "BBB+.IL",
          "S&P מעלות",
          "30/04/18",
          4.94,
          "שקל חדש",
          4.8,
          0.06,
          1252606.49,
          95.48,
          0.0,
          1195.988676652,
          0.05,
          2.2,
          1.16
        ],
        [
          "נובל אגח א- נובל אסטס(בי.וי.איי)לימיטד",
          1141860,
          "TASE",
          "אחר",
          1699,
          "נדל\"ן ובינוי",
          "BBB+.IL",
          "S&P מעלות",
          "13/09/17",
          4.04,
          "שקל חדש",
          6.75,
          0.09,
          307960.0,
          94.5,
          0.0,
          291.0222,
          0.09,
          0.54,
          0.28
        ],
        [
          "סקייליין אגח א",
          1138775,
          "TASE",
          "אחר",
          1613,
          "נדל\"ן ובינוי",
          "Baa1.IL",
          "מידרוג",
          "29/08/17",
          "",
          "שקל חדש",
          5.2,
          0.0,
          170769.25,
          106.6,
          0.0,
          182.0400205,
          0.0,
          0.33,
          0.18
        ],
        [
          "צמח המרמן אגח ד- צ.מ.ח המרמן בע\"מ",
          1134873,
          "TASE",
          "אחר",
          512531203,
          "נדל\"ן ובינוי",
          "Baa1.IL",
          "מידרוג",
          "25/09/17",
          1.31,
          "שקל חדש",
          5.5,
          0.03,
          159474.75,
          104.41,
          0.0,
          166.507586475,
          0.07,
          0.31,
          0.16
        ],
        [
          "צרפתי אג\"ח ח- צבי צרפתי ובניו השקעות ובנין (1992) בע\"מ",
          4250189,
          "TASE",
          "אחר",
          520039090,
          "נדל\"ן ובינוי",
          "BBB+.IL",
          "S&P מעלות",
          "16/05/16",
          1.52,
          "שקל חדש",
          3.95,
          0.03,
          137700.01,
          102.6,
          0.0,
          141.28021026,
          0.15,
          0.26,
          0.14
        ],
        [
          "רבד ג- רבד בע\"מ",
          5260096,
          "TASE",
          "אחר",
          520040148,
          "נדל\"ן ובינוי",
          "Baa1.IL",
          "מידרוג",
          "03/01/16",
          3.67,
          "שקל חדש",
          5.75,
          0.04,
          153640.01,
          106.0,
          0.0,
          162.8584106,
          0.2,
          0.3,
          0.16
        ],
        [
          "אידיביפת אגח יד- אידיבי חברה לפתוח בע\"מ",
          7980337,
          "TASE",
          "אחר",
          520032285,
          "השקעה ואחזקות",
          "BB.IL",
          "S&P מעלות",
          "26/07/17",
          3.83,
          "שקל חדש",
          5.0,
          0.08,
          312000.0,
          89.36,
          3.9,
          282.7032,
          0.03,
          0.52,
          0.27
        ],
        [
          "בוניתיכון אגחיג- בוני התיכון הנדסה אזרחית ותשתיות בע\"מ",
          5310164,
          "TASE",
          "אחר",
          520040304,
          "נדל\"ן ובינוי",
          "NR",
          "לא מדורג",
          "18/07/17",
          1.31,
          "שקל חדש",
          4.1,
          0.03,
          140109.95,
          102.6,
          0.0,
          143.7528087,
          0.37,
          0.26,
          0.14
        ],
        [
          "חלל תקשורת ט- חלל-תקשורת בע\"מ",
          1131424,
          "TASE",
          "אחר",
          511396046,
          "תקשורת ומדיה",
          "NR",
          "לא מדורג",
          "11/09/16",
          0.98,
          "שקל חדש",
          6.3,
          0.04,
          0.12,
          101.66,
          0.0,
          0.000121992,
          0.0,
          0.0,
          0.0
        ],
        [
          "מירלנד אגח ז- מירלנד דיוולופמנט קורפריישן פי אל סי",
          1139559,
          "TASE",
          "אחר",
          1502,
          "נדל\"ן ובינוי",
          "NR",
          "לא מדורג",
          "23/01/17",
          4.05,
          "שקל חדש",
          1.0,
          0.12,
          175820.08,
          65.99,
          0.0,
          116.023670792,
          0.06,
          0.21,
          0.11
        ],
        [
          "נתנאל גרופ אגחו- נתנאל גרופ בע\"מ",
          4210126,
          "TASE",
          "אחר",
          520039074,
          "נדל\"ן ובינוי",
          "NR",
          "לא מדורג",
          "24/01/16",
          1.91,
          "שקל חדש",
          5.5,
          2.82,
          156000.0,
          106.24,
          0.0,
          165.7344,
          0.4,
          0.3,
          0.16
        ],
        [
          "נתנאל גרופט ט- נתנאל גרופ בע\"מ",
          4210142,
          "TASE",
          "אחר",
          520039074,
          "נדל\"ן ובינוי",
          "NR",
          "לא מדורג",
          "03/08/17",
          3.11,
          "שקל חדש",
          4.85,
          0.06,
          320984.0,
          98.59,
          0.0,
          316.4581256,
          0.32,
          0.58,
          0.31
        ],
        [
          "פרשקובסקי אגח י- פרשקובסקי השקעות ובניין בע\"מ",
          1139997,
          "TASE",
          "אחר",
          513817817,
          "נדל\"ן ובינוי",
          "NR",
          "לא מדורג",
          "31/01/17",
          1.72,
          "שקל חדש",
          3.1,
          0.03,
          78000.0,
          100.3,
          1.209,
          79.443,
          0.08,
          0.15,
          0.08
        ],
        [
          "רציו מימון ב- רציו חיפושי נפט (מימון) בע\"מ",
          1139443,
          "TASE",
          "אחר",
          515060044,
          "חיפושי נפט וגז",
          "NR",
          "לא מדורג",
          "10/01/17",
          3.73,
          "שקל חדש",
          2.0,
          0.05,
          365539.0,
          116.76,
          0.0,
          426.8033364,
          0.06,
          0.78,
          0.41
        ],
        [
          "ישראמקו נגב 2 א' 2018/2025 %3.49- ישראמקו נגב 2 שותפות מוגבלת",
          2320174,
          "TASE",
          "אחר",
          550010003,
          "חיפושי נפט וגז",
          "AA.IL",
          "S&P מעלות",
          "29/04/18",
          3.62,
          "שקל חדש",
          3.49,
          0.04,
          115000.0,
          98.39,
          0.0,
          113.1485,
          0.01,
          0.21,
          0.11
        ],
        [
          "פננטפארק אגח א- פננטפארק",
          1142371,
          "TASE",
          "אחר",
          2246,
          "אחר",
          "AA-.IL",
          "S&P מעלות",
          "29/08/18",
          3.93,
          "שקל חדש",
          3.83,
          0.05,
          273590.0,
          97.78,
          0.0,
          267.516302,
          0.06,
          0.49,
          0.26
        ],
        [
          "דלק קידוחים א- דלק קידוחים - שותפות מוגבלת",
          4750089,
          "TASE",
          "אחר",
          550013098,
          "חיפושי נפט וגז",
          "A1.IL",
          "מידרוג",
          "22/01/18",
          3.04,
          "שקל חדש",
          4.5,
          0.05,
          369179.0,
          95.14,
          0.0,
          351.2369006,
          0.02,
          0.65,
          0.34
        ],
        [
          "תמר פטרו אגח ב- תמר פטרוליום בע\"מ",
          1143593,
          "TASE",
          "אחר",
          515334662,
          "חיפושי נפט וגז",
          "A1.IL",
          "מידרוג",
          "13/03/18",
          5.63,
          "שקל חדש",
          4.69,
          0.06,
          145116.0,
          98.7,
          0.0,
          143.229492,
          0.01,
          0.26,
          0.14
        ],
        [
          "תמר פטרול א- תמר פטרוליום בע\"מ",
          1141332,
          "TASE",
          "אחר",
          515334662,
          "חיפושי נפט וגז",
          "A1.IL",
          "מידרוג",
          "22/01/18",
          5.53,
          "שקל חדש",
          4.69,
          0.06,
          1007776.19,
          97.42,
          0.0,
          981.775564298,
          0.04,
          1.8,
          0.95
        ],
        [
          "חברה לישראל 11- החברה לישראל בע\"מ",
          5760244,
          "TASE",
          "אחר",
          520028010,
          "השקעה ואחזקות",
          "A.IL",
          "S&P מעלות",
          "19/01/17",
          3.33,
          "שקל חדש",
          5.25,
          0.05,
          403389.0,
          98.19,
          0.0,
          396.0876591,
          0.03,
          0.73,
          0.38
        ],
        [
          "בזן אגח ו- בתי זקוק לנפט בע\"מ",
          2590396,
          "TASE",
          "אחר",
          520036658,
          "חיפושי נפט וגז",
          "A-.IL",
          "S&P מעלות",
          "05/02/18",
          3.22,
          "שקל חדש",
          6.7,
          0.05,
          333389.0,
          100.87,
          0.0,
          336.2894843,
          0.03,
          0.62,
          0.33
        ],
        [
          "סקייליין אגח ב- סקייליין אינווסטמנטס אינק",
          1142033,
          "TASE",
          "אחר",
          1613,
          "נדל\"ן ובינוי",
          "Baa1.IL",
          "מידרוג",
          "06/11/17",
          4.07,
          "שקל חדש",
          5.65,
          0.07,
          411549.0,
          99.6,
          0.0,
          409.902804,
          0.25,
          0.75,
          0.4
        ],
        [
          "חלל תקש אג יז- חלל-תקשורת בע\"מ",
          1140888,
          "TASE",
          "אחר",
          511396046,
          "תקשורת ומדיה",
          "NR",
          "לא מדורג",
          "18/01/18",
          4.49,
          "שקל חדש",
          5.5,
          0.1,
          446610.0,
          83.0,
          0.0,
          370.6863,
          0.19,
          0.68,
          0.36
        ],
        [
          "חלל תקש אגח טז- חלל-תקשורת בע\"מ",
          1139922,
          "TASE",
          "אחר",
          511396046,
          "תקשורת ומדיה",
          "NR",
          "לא מדורג",
          "29/01/17",
          4.56,
          "שקל חדש",
          5.95,
          0.07,
          334626.0,
          90.69,
          0.0,
          303.4723194,
          0.03,
          0.56,
          0.29
        ],
        [
          "רציו מימון אגחג- רציו חיפושי נפט (מימון) בע\"מ",
          1142488,
          "TASE",
          "אחר",
          515060044,
          "חיפושי נפט וגז",
          "NR",
          "לא מדורג",
          "18/01/18",
          3.61,
          "שקל חדש",
          2.21,
          0.07,
          294272.0,
          104.98,
          0.0,
          308.9267456,
          0.05,
          0.57,
          0.3
        ],
        [
          "DELAVN4.4301220- דלק&אבנר",
          "IL0011321663",
          "NYSE",
          "בלומברג",
          5192,
          "Energy",
          "BBB-",
          "S&P",
          "03/01/16",
          4.13,
          "דולר אמריקאי",
          4.44,
          2.1,
          40800.0,
          101.79611102941176,
          0.0,
          149.4765950667,
          0.01,
          0.27,
          0.14
        ],
        [
          "TEVA 3.15 10/01/26- TEVA PHARMACEUTICAL INDU",
          "US88167AAE10",
          "NYSE",
          "בלומברג",
          29786,
          "Health Care Equipment & Services",
          "BB",
          "S&P",
          "14/12/17",
          5.72,
          "דולר אמריקאי",
          3.15,
          6.84,
          69000.0,
          83.711,
          3.91121325,
          211.79157666,
          0.0,
          0.39,
          0.2
        ],
        [
          "TEVA 6 3/4 03/01/28- TEVA PHARMACEUTICAL INDU",
          "US88167AAK79",
          "NYSE",
          "בלומברג",
          29786,
          "Pharmaceuticals & Biotechnology",
          "Ba2",
          "Moodys",
          "28/05/18",
          6.01,
          "דולר אמריקאי",
          6.75,
          6.94,
          107000.0,
          105.82731504672897,
          0.0,
          407.5335823329,
          0.01,
          0.75,
          0.39
        ],
        [
          "CDEL 4 1/2 08/13/23- CODELCO INC",
          "USP3143NAR54",
          "אחר",
          "בלומברג",
          29588,
          "Materials",
          "A3",
          "Moodys",
          "30/01/17",
          4.01,
          "דולר אמריקאי",
          4.5,
          4.32,
          92000.0,
          102.69979456521739,
          0.0,
          340.047235789,
          0.01,
          0.63,
          0.33
        ],
        [
          "C 4 1/5 01/14/22- CITIGROUP INC",
          "US172967FT34",
          "NYSE",
          "בלומברג",
          5263,
          "Banks",
          "BBB+",
          "S&P",
          "03/01/16",
          3.56,
          "דולר אמריקאי",
          4.5,
          3.01,
          52000.0,
          103.81232884615385,
          0.0,
          194.282697189,
          0.0,
          0.36,
          0.19
        ],
        [
          "HYNMTR 3.1 04/05/22- HYUNDAI CAPITAL AMERICA",
          "US44891CAM55",
          "NYSE",
          "בלומברג",
          30110,
          "Automobiles & Components",
          "Baa1",
          "Moodys",
          "19/10/17",
          4,
          "דולר אמריקאי",
          3.1,
          3.24,
          153000.0,
          97.119,
          8.5350285,
          543.31788843,
          0.03,
          1.0,
          0.53
        ],
        [
          "RABOBK 4 04/10/29- COOPERATIEVE RABOBANK UA",
          "XS1592433038",
          "אחר",
          "בלומברג",
          30038,
          "Diversified Financials",
          "BBB+",
          "S&P",
          "24/01/18",
          4.84,
          "דולר אמריקאי",
          4.0,
          4.79,
          105000.0,
          98.29397257142857,
          0.0,
          371.4480076488,
          0.02,
          0.68,
          0.36
        ],
        [
          "SRENVX 5 3/4 08/15/50- DEMETER(SWISS RE LTD(",
          "XS1261170515",
          "אחר",
          "בלומברג",
          29764,
          "אחר",
          "BBB+",
          "S&P",
          "23/01/18",
          5.86,
          "דולר אמריקאי",
          5.75,
          5.53,
          90000.0,
          102.10039722222223,
          0.0,
          330.7133966425,
          0.01,
          0.61,
          0.32
        ],
        [
          "WFC 4.1 06/03/26- WELLS FARGO & COMPANY",
          "US94974BFY11",
          "NYSE",
          "בלומברג",
          5579,
          "Banks",
          "BBB+",
          "S&P",
          "14/12/17",
          4.29,
          "דולר אמריקאי",
          4.1,
          6.43,
          85000.0,
          100.10478082352941,
          0.0,
          306.2355402563,
          0.0,
          0.56,
          0.3
        ],
        [
          "BAYNGR 4 1/4 12/15/25- BAYER US FINANCE II LLC",
          "USU07265AE85",
          "NYSE",
          "בלומברג",
          30207,
          "Pharmaceuticals & Biotechnology",
          "BBB",
          "S&P",
          "25/06/18",
          4.34,
          "דולר אמריקאי",
          4.25,
          6.08,
          20000.0,
          100.5551645,
          0.0,
          72.3796074071,
          0.0,
          0.13,
          0.07
        ],
        [
          "BHP 6 1/4 10/19/75",
          "USQ12441AA19",
          "NYSE",
          "בלומברג",
          28046,
          "Materials",
          "Baa2",
          "Moodys",
          "12/07/18",
          "",
          "דולר אמריקאי",
          6.25,
          2.08,
          75000.0,
          107.4116028,
          0.0,
          289.9307688579,
          0.01,
          0.53,
          0.28
        ],
        [
          "FISV 3.85 06/01/25- FISERV INC",
          "US337738AP30",
          "NYSE",
          "בלומברג",
          29703,
          "Diversified Financials",
          "BBB",
          "S&P",
          "25/09/17",
          3.85,
          "דולר אמריקאי",
          3.85,
          5.75,
          61000.0,
          100.53720540983606,
          0.0,
          220.7183753847,
          0.01,
          0.41,
          0.21
        ],
        [
          "HPE 4.9 10/15/25- HP ENTERPRISE CO",
          "US42824CAW91",
          "NYSE",
          "בלומברג",
          29742,
          "Software & Services",
          "BBB",
          "S&P",
          "04/01/17",
          4.42,
          "דולר אמריקאי",
          4.9,
          5.8,
          58000.0,
          105.11661103448276,
          0.0,
          219.4225162056,
          0.0,
          0.4,
          0.21
        ],
        [
          "C 4.4 06/10/25- CITIGROUP INC",
          "US172967JT97",
          "NYSE",
          "בלומברג",
          28128,
          "Banks",
          "Baa3",
          "Moodys",
          "23/01/18",
          4.41,
          "דולר אמריקאי",
          4.4,
          5.67,
          59000.0,
          101.20891779661017,
          0.0,
          214.9080281385,
          0.0,
          0.4,
          0.21
        ],
        [
          "KRFT 3 1/2 06/06/22- Kraft foods Inc",
          "US50076QAZ90",
          "NYSE",
          "בלומברג",
          5538,
          "Consumer Durables & Apparel",
          "Baa3",
          "Moodys",
          "03/01/16",
          3.71,
          "דולר אמריקאי",
          3.5,
          3.38,
          50000.0,
          100.3608888,
          0.0,
          180.5994193956,
          0.0,
          0.33,
          0.17
        ],
        [
          "PEMEX 5 1/2 01/21/21- PETROLEOS MEXICANOS",
          "US71654QAX07",
          "NYSE",
          "בלומברג",
          29479,
          "Energy",
          "Baa3",
          "Moodys",
          "03/01/16",
          4.13,
          "דולר אמריקאי",
          5.5,
          2.13,
          90000.0,
          104.07561111111112,
          0.0,
          337.11131195,
          0.0,
          0.62,
          0.33
        ],
        [
          "TRPCN 5 5/8 05/20/75- TRANSCANADA TRUST",
          "US89356BAA61",
          "TSX",
          "בלומברג",
          29981,
          "Energy",
          "BBB-",
          "S&P",
          "14/12/17",
          5.13,
          "דולר אמריקאי",
          5.63,
          5.35,
          112000.0,
          100.586,
          0.0,
          405.45009568,
          0.01,
          0.75,
          0.39
        ],
        [
          "CIELBZ 3 3/4 11/16/22- CIELO SA/CIELO USA INC",
          "USP28610AA46",
          "NYSE",
          "בלומברג",
          30134,
          "Consumer Durables & Apparel",
          "Ba1",
          "Moodys",
          "14/12/17",
          5.61,
          "דולר אמריקאי",
          3.75,
          3.69,
          90000.0,
          94.61898633333334,
          0.0,
          306.4803586323,
          0.01,
          0.56,
          0.3
        ],
        [
          "LB 6.694 01/15/27- L BRANDS INC",
          "USU51407AC50",
          "NYSE",
          "בלומברג",
          29577,
          "Retailing",
          "BB",
          "S&P",
          "21/06/18",
          "",
          "דולר אמריקאי",
          6.69,
          0.0,
          64000.0,
          96.24565203125,
          0.0,
          221.6883850627,
          0.02,
          0.41,
          0.21
        ],
        [
          "VRSN 4 5/8 05/01/23- VERISIGN INC",
          "US92343EAF97",
          "NYSE",
          "בלומברג",
          29794,
          "Media",
          "Ba2",
          "Moodys",
          "30/03/17",
          4.41,
          "דולר אמריקאי",
          4.63,
          4.02,
          71140.0,
          103.4126849873489,
          0.0,
          264.7704549759,
          0.01,
          0.49,
          0.26
        ]
      ]
    },
    "חוזים עתידיים": {
      "columns": [
        "שם המנפיק/שם נייר ערך",
        "מספר ני\"ע",
        "זירת מסחר",
        "ענף מסחר",
        "סוג מטבע",
        "ערך נקוב",
        "שער",
        "שווי שוק",
        "שעור מנכסי אפיק ההשקעה",
        "שעור מסך נכסי השקעה",
        "ASX",
        "אוסטרליה",
        "בנקים וחברות אחזקה",
        "untitled1",
        "אירו"
      ],
      "data": [
        [
          "EURO BUND FUT D התחייבות- EURO-BUND FUTURE",
          730336561,
          "אחר",
          "Diversified Financials",
          "אירו",
          642960.0,
          100.0,
          2710.333584,
          3040016.03,
          2.62,
          "",
          "",
          "",
          "שירותים",
          ""
        ],
        [
          "EURO-BUND FUTURE  Dec18- EURO-BUND FUTURE",
          "DE000C1J3KW7",
          "FWB",
          "Diversified Financials",
          "אירו",
          -4.0,
          15806000.0,
          -2665.144496,
          -2989330.18,
          -2.58,
          "",
          "",
          "",
          "שירותים פיננסיים",
          ""
        ],
        [
          "US 2YR NOTE (CBT) Dec18- US 2YR NOTE",
          73033649,
          "NYSE",
          "Diversified Financials",
          "דולר אמריקאי",
          3.0,
          21068750.0,
          2274.7929375,
          2551496.62,
          2.2,
          "",
          "",
          "",
          "תוכנה ואינטרנט",
          ""
        ],
        [
          "US 5YR NOTE (CBT) Dec18- US 5yr NOTE (CBT) MAR18",
          73033672,
          "NYSE",
          "Diversified Financials",
          "דולר אמריקאי",
          10.0,
          11242187.5,
          4046.06328125,
          4538222.63,
          3.91,
          "",
          "",
          "",
          "תיירות ומלונות",
          ""
        ],
        [
          "US 5YR NOTE CBT התחייבות- US 5yr NOTE (CBT) MAR18",
          730336721,
          "אחר",
          "Diversified Financials",
          "דולר אמריקאי",
          -1134687.5,
          100.0,
          -4083.7403125,
          -4580482.66,
          -3.95,
          "",
          "",
          "",
          "תעשייה שונות",
          ""
        ],
        [
          "US 2YR NOTE CBT התחייבות- הבנק הבינלאומי הראשון לישראל בע\"מ",
          730336491,
          "אחר",
          "Diversified Financials",
          "דולר אמריקאי",
          -634125.0,
          100.0,
          -2282.215875,
          -2559822.48,
          -2.21,
          "",
          "",
          "",
          "תקשורת ומדיה",
          ""
        ],
        [
          "US 2YR NOTE JUN18 התחייבות- הבנק הבינלאומי הראשון לישראל בע\"מ",
          730307851,
          "אחר",
          "Diversified Financials",
          "דולר אמריקאי",
          0.01,
          100.0,
          3.599e-05,
          0.04,
          0.0,
          "",
          "",
          "",
          "אחר",
          ""
        ]
      ]
    },
    "מוצרים מובנים": {
      "columns": [
        "שם המנפיק/שם נייר ערך",
        "מספר ני\"ע",
        "נכס הבסיס",
        "דירוג",
        "שם מדרג",
        "תאריך רכישה",
        "מח\"מ",
        "סוג מטבע",
        "שיעור ריבית",
        "תשואה לפידיון",
        "ערך נקוב",
        "שער",
        "שווי שוק",
        "שעור מערך נקוב מונפק",
        "שעור מנכסי אפיק ההשקעה",
        "שעור מסך נכסי השקעה"
      ],
      "data": [
        [
          "אלה פקדון אגח ב (אג\"ח מובנה)- אלה פקדונות בע\"מ",
          1142215,
          "רביות",
          "AAA.IL",
          "S&P מעלות",
          "14/02/18",
          4.03,
          "שקל חדש",
          0.62,
          0.0,
          327929,
          102.76,
          336.9798404,
          0.01,
          70.35,
          0.33
        ],
        [
          "דולר טריפל איי א 2.9%",
          1141662,
          "מטבעות",
          "AAA.IL",
          "S&P מעלות",
          "21/08/17",
          4.62,
          "שקל חדש",
          2.9,
          0.03,
          145445,
          97.66,
          142.041587,
          0.02,
          29.65,
          0.14
        ]
      ]
    },
    "לא סחיר - אג\"ח קונצרני": {
      "columns": [
        "שם המנפיק/שם נייר ערך",
        "מספר ני\"ע",
        "ספק המידע",
        "מספר מנפיק",
        "ענף מסחר",
        "דירוג",
        "שם מדרג",
        "תאריך רכישה",
        "מח\"מ",
        "סוג מטבע",
        "שיעור ריבית",
        "תשואה לפידיון",
        "ערך נקוב",
        "שער",
        "שווי הוגן",
        "שעור מערך נקוב מונפק",
        "שעור מנכסי אפיק ההשקעה",
        "שעור מסך נכסי השקעה"
      ],
      "data": [
        [
          "מימון ישיר הנפקות (סדרה 2) בע\"מ SPC- מימון ישיר הנפקות (סדרה 2) בע\"מ SPC",
          1136035,
          "אחר",
          1647,
          "שירותים פיננסיים",
          "AAA.IL",
          "S&P מעלות",
          "16/07/15",
          0.75,
          "שקל חדש",
          1.95,
          0.28,
          19912.5,
          102.03,
          20.31672375,
          0.01,
          0.89,
          0.02
        ],
        [
          "רפאל אגח ג-רמ- רפאל-רשות לפיתוח אמצעי לחימה בע\"מ",
          1140276,
          "אחר",
          1315,
          "Energy",
          "Aaa.IL",
          "מידרוג",
          "02/03/17",
          8.19,
          "שקל חדש",
          2.14,
          1.38,
          102000.0,
          108.12,
          110.2824,
          0.04,
          4.84,
          0.11
        ],
        [
          "מימון ישיר אגח6-רמ- מימון ישיר הנפקות (סדרה חדשה 6)",
          1145606,
          "אחר",
          515631026,
          "שירותים פיננסיים",
          "Aa2.IL",
          "מידרוג",
          "09/05/18",
          2.65,
          "שקל חדש",
          2.1,
          2.14,
          199525.71,
          101.12,
          201.760397952,
          0.05,
          8.86,
          0.2
        ],
        [
          "מימון ישיר אגח7-רמ- מימון ישיר הנפקות (סדרה 7)",
          1153071,
          "אחר",
          515828820,
          "שירותים פיננסיים",
          "AA.IL",
          "S&P מעלות",
          "13/08/18",
          2.23,
          "שקל חדש",
          2.95,
          2.93,
          255206.64,
          100.34,
          256.074342576,
          0.08,
          11.25,
          0.25
        ],
        [
          "מימון ישיר הנפקות (סדרה 4) בע\"מ SPC- מימון ישיר הנפקות (סדרה 4) בע\"מ SPC",
          1142637,
          "אחר",
          30142,
          "שירותים פיננסיים",
          "Aa2.IL",
          "מידרוג",
          "10/12/17",
          2.39,
          "שקל חדש",
          1.9,
          1.77,
          157914.15,
          101.21,
          159.824911215,
          0.0,
          7.02,
          0.15
        ],
        [
          "מימון ישיר אג א - רמ",
          1139740,
          "אחר",
          1647,
          "שירותים פיננסיים",
          "A2.IL",
          "מידרוג",
          "22/12/16",
          2.39,
          "שקל חדש",
          3.15,
          2.76,
          219165.01,
          103.16,
          226.090624316,
          0.05,
          9.93,
          0.22
        ],
        [
          "אמפל אמרי אגח ב",
          1110378,
          "אחר",
          2023,
          "השקעה ואחזקות",
          "C.IL",
          "מידרוג",
          "03/01/16",
          0.74,
          "שקל חדש",
          6.6,
          0.0,
          74420.0,
          11.2,
          8.33504,
          0.01,
          0.37,
          0.01
        ],
        [
          "אמפל מא ב חש 1/12",
          1125624,
          "אחר",
          2023,
          "השקעה ואחזקות",
          "C.IL",
          "מידרוג",
          "03/01/16",
          0.74,
          "שקל חדש",
          6.6,
          0.0,
          74420.0,
          11.2,
          8.33504,
          0.0,
          0.37,
          0.01
        ],
        [
          "אמפלאמ ב חש1/13",
          1127679,
          "אחר",
          2023,
          "השקעה ואחזקות",
          "C.IL",
          "מידרוג",
          "03/01/16",
          0.74,
          "שקל חדש",
          6.6,
          0.0,
          74420.0,
          11.2,
          8.33504,
          0.0,
          0.37,
          0.01
        ],
        [
          "אמפלאמ ב חש1/14 אנליסט- אמפל אמריקן ישראל קורפוריישן",
          113118418,
          "אחר",
          2023,
          "השקעה ואחזקות",
          "C.IL",
          "מידרוג",
          "03/01/16",
          0.74,
          "שקל חדש",
          6.6,
          0.0,
          74420.0,
          11.2,
          8.33504,
          0.0,
          0.37,
          0.01
        ],
        [
          "אמפלאמ ב חש2/15",
          1134394,
          "אחר",
          2023,
          "השקעה ואחזקות",
          "NR",
          "לא מדורג",
          "03/01/16",
          0.74,
          "שקל חדש",
          6.6,
          0.0,
          74420.0,
          11.2,
          8.33504,
          0.0,
          0.37,
          0.01
        ],
        [
          "בסר אירופ אגח ט",
          1170166,
          "אחר",
          117,
          "נדל\"ן ובינוי",
          "NR",
          "לא מדורג",
          "03/01/16",
          "",
          "שקל חדש",
          7.1,
          0.0,
          6500.0,
          42.2,
          2.743,
          0.01,
          0.12,
          0.0
        ],
        [
          "בסר אירופ ט חש 12/12",
          1170190,
          "אחר",
          117,
          "נדל\"ן ובינוי",
          "NR",
          "לא מדורג",
          "03/01/16",
          0,
          "שקל חדש",
          7.1,
          0.0,
          2166.67,
          42.2,
          0.91433474,
          0.0,
          0.04,
          0.0
        ],
        [
          "פרופיט אגח ד- פרופיט תעשיות בניה בע\"מ",
          5490123,
          "אחר",
          549,
          "נדל\"ן ובינוי",
          "NR",
          "לא מדורג",
          "15/06/16",
          0.94,
          "שקל חדש",
          5.8,
          79.26,
          43527.02,
          9.96,
          4.335291192,
          0.06,
          0.19,
          0.0
        ],
        [
          "רפאל אגח ה-רמ- רפאל-רשות לפיתוח אמצעי לחימה בע\"מ",
          1140292,
          "אחר",
          1315,
          "Energy",
          "Aaa.IL",
          "מידרוג",
          "02/03/17",
          4.23,
          "שקל חדש",
          2.5,
          1.93,
          102000.0,
          102.53,
          104.5806,
          0.01,
          4.59,
          0.1
        ],
        [
          "מת\"מ אגח א-רמ- מת\"מ - מרכז תעשיות מדע חיפה בע\"מ",
          1138999,
          "אחר",
          1666,
          "נדל\"ן ובינוי",
          "Aa2.IL",
          "מידרוג",
          "17/08/16",
          5.63,
          "שקל חדש",
          3.1,
          2.66,
          97200.01,
          103.42,
          100.524250342,
          0.03,
          4.42,
          0.1
        ],
        [
          "אליהו הנפקות א- אליהו הנפקות בע\"מ",
          1142009,
          "אחר",
          515703528,
          "ביטוח",
          "A1.IL",
          "מידרוג",
          "28/09/17",
          4.69,
          "שקל חדש",
          3.85,
          4.05,
          276785.0,
          99.33,
          274.9305405,
          0.02,
          12.08,
          0.27
        ],
        [
          "אלטשולר אגח א - רמ- אלטשולר שחם",
          1139336,
          "אחר",
          1669,
          "השקעה ואחזקות",
          "A2.IL",
          "מידרוג",
          "06/10/16",
          2.41,
          "שקל חדש",
          3.42,
          2.6,
          147438.4,
          103.58,
          152.71669472,
          0.07,
          6.71,
          0.15
        ],
        [
          "ביטוח ישיר אגח יא- ביטוח ישיר - השקעות פיננסיות בע\"מ",
          1138825,
          "אחר",
          520044439,
          "ביטוח",
          "A2.IL",
          "מידרוג",
          "22/07/16",
          5.37,
          "שקל חדש",
          4.6,
          3.41,
          139040.01,
          107.72,
          149.773898772,
          0.02,
          6.58,
          0.14
        ],
        [
          "י.ח.ק השקעות א'2018/2021 2.57%- י.ח.ק השקעות",
          1143007,
          "אחר",
          550016091,
          "השקעה ואחזקות",
          "A-.IL",
          "S&P מעלות",
          "15/01/18",
          1.98,
          "שקל חדש",
          2.57,
          3.33,
          262000.0,
          99.19,
          259.8778,
          0.0,
          11.42,
          0.25
        ],
        [
          "שמוס אגח א - רמ- שמוס אינטרנשיונל לימיטד",
          1147578,
          "אחר",
          1742,
          "נדל\"ן ובינוי",
          "Aa3.IL",
          "מידרוג",
          "06/06/18",
          6.43,
          "שקל חדש",
          5.1,
          4.45,
          210000.0,
          100.01,
          210.021,
          0.01,
          9.23,
          0.2
        ]
      ]
    },
    "לא סחיר - קרנות השקעה": {
      "columns": [
        "שם המנפיק/שם נייר ערך",
        "מספר ני\"ע",
        "סוג מטבע",
        "תאריך רכישה",
        "ערך נקוב",
        "שער",
        "שווי הוגן",
        "שעור מערך נקוב מונפק",
        "שעור מנכסי אפיק ההשקעה",
        "שעור מסך נכסי השקעה"
      ],
      "data": [
        [
          "קוגיטו בי.אם.אי",
          400050917,
          "שקל חדש",
          "26/09/18",
          55571.91,
          104.9351,
          58.31443933041,
          0,
          63.23,
          0.06
        ],
        [
          "קרן קוגיטו קפיטל ממשלתי",
          400090117,
          "שקל חדש",
          "27/09/18",
          39642.77,
          85.5577,
          33.91744222829,
          0,
          36.77,
          0.03
        ]
      ]
    },
    "לא סחיר - חוזים עתידיים": {
      "columns": [
        "שם המנפיק/שם נייר ערך",
        "מספר ני\"ע",
        "ענף מסחר",
        "סוג מטבע",
        "תאריך רכישה",
        "ערך נקוב",
        "שער",
        "שווי הוגן",
        "שעור מנכסי אפיק ההשקעה",
        "שעור מסך נכסי השקעה"
      ],
      "data": [
        [
          "ILS-USD 0003.589100 20181031 20180927",
          570001030,
          "אחר",
          "דולר אמריקאי",
          "27/09/18",
          -2335000,
          0.12207216494845397,
          -2.8503850515464,
          100,
          0
        ]
      ]
    },
    "לא סחיר - מוצרים מובנים": {
      "columns": [
        "שם המנפיק/שם נייר ערך",
        "מספר ני\"ע",
        "נכס הבסיס",
        "דירוג",
        "שם מדרג",
        "תאריך רכישה",
        "מח\"מ",
        "סוג מטבע",
        "שיעור ריבית",
        "תשואה לפידיון",
        "ערך נקוב",
        "שער",
        "שווי הוגן",
        "שעור מערך נקוב מונפק",
        "שעור מנכסי אפיק ההשקעה",
        "שעור מסך נכסי השקעה"
      ],
      "data": [
        [
          "אפריל נדלן ב-ל- אפריל נדל\"ן החזקות 2012 בע\"מ",
          1127273,
          "מניות",
          "NR",
          "לא מדורג",
          "03/01/16",
          1.94,
          "שקל חדש",
          2,
          1.6,
          27048,
          4.51,
          1.2198648,
          0.03,
          100,
          0
        ]
      ]
    },
    "הלוואות": {
      "columns": [
        "שם ני\"ע",
        "קונסורציום כן/לא",
        "מספר ני\"ע",
        "מספר מנפיק",
        "דירוג",
        "תאריך רכישה",
        "שם מדרג",
        "מח\"מ",
        "סוג מטבע",
        "שיעור ריבית ממוצע",
        "תשואה לפידיון",
        "ערך נקוב",
        "שער",
        "שווי הוגן",
        "שעור מנכסי אפיק ההשקעה",
        "שעור מסך נכסי השקעה",
        "מעלות",
        "שקל חדש"
      ],
      "data": [
        [
          "שווי לא צמוד 754 אנליסט גמל אג\"ח",
          "לא",
          91453001,
          29539,
          "AA+",
          "19/08/18",
          "פנימי",
          3.06,
          "שקל חדש",
          1.1,
          1.13,
          2195055.84,
          100.7217,
          2210.89755799728,
          100,
          2.14,
          "",
          ""
        ]
      ]
    }
  }
}